Workbook

Sheet raw data
A1: Download Page | B1: H.8 Assets and Liabilities of Commercial Banks in the United States for Mar 18, 2022
A2: Series Description | B2: Bank credit, all commercial banks, seasonally adjusted | C2: Securities in bank credit, all commercial banks, seasonally adjusted | D2: Treasury and agency securities, all commercial banks, seasonally adjusted | E2: Treasury and agency securities: Mortgage-backed securities (MBS), all commercial banks, seasonally adjusted | F2: Treasury and agency securities: Non-MBS, all commercial banks, seasonally adjusted | G2: Other securities, all commercial banks, seasonally adjusted | H2: Other securities: Mortgage-backed securities, all commercial banks, seasonally adjusted | I2: Other securities: Non-MBS, all commercial banks, seasonally adjusted | J2: Loans and leases in bank credit, all commercial banks, seasonally adjusted | K2: Commercial and industrial loans, all commercial banks, seasonally adjusted | L2: Real estate loans, all commercial banks, seasonally adjusted | M2: Real estate loans: Residential real estate loans, all commercial banks, seasonally adjusted | N2: Real estate loans: Residential real estate loans: Revolving home equity loans, all commercial banks, seasonally adjusted | O2: Real estate loans: Residential real estate loans: Closed-end residential loans, all commercial banks, seasonally adjusted | P2: Real estate loans: Commercial real estate loans, all commercial banks, seasonally adjusted | Q2: Real estate loans: Commercial real estate loans: Construction and land development loans, all commercial banks, seasonally adjusted | R2: Real estate loans: Commercial real estate loans: Secured by farmland, all commercial banks, seasonally adjusted | S2: Real estate loans: Commercial real estate loans: Secured by multifamily properties, all commercial banks, seasonally adjusted | T2: Real estate loans: Commercial real estate loans: Secured by nonfarm nonresidential properties, all commercial banks, seasonally adjusted | U2: Consumer loans, all commercial banks, seasonally adjusted | V2: Consumer loans: Credit cards and other revolving plans, all commercial banks, seasonally adjusted | W2: Consumer loans: Other consumer loans, all commercial banks, seasonally adjusted | X2: Consumer loans: Other consumer loans: Automobile loans, all commercial banks, seasonally adjusted | Y2: Consumer loans: Other consumer loans: All other consumer loans, all commercial banks, seasonally adjusted | Z2: Other loans and leases: All other loans and leases, all commercial banks, seasonally adjusted | AA2: Other loans and leases: All other loans and leases: Loans to nondepository financial institutions, all commercial banks, seasonally adjusted | AB2: Other loans and leases: All other loans and leases: Other loans not elsewhere classified, all commercial banks, seasonally adjusted | AC2: LESS: Allowance for loan and lease losses, all commercial banks, seasonally adjusted | AD2: Cash assets, all commercial banks, seasonally adjusted | AE2: Federal funds sold and securities purchased under agreement to resell | AF2: Loans to commercial banks, all commercial banks, seasonally adjusted | AG2: Other assets, all commercial banks, seasonally adjusted | AH2: Total assets, all commercial banks, seasonally adjusted | AI2: Deposits, all commercial banks, seasonally adjusted | AJ2: Large time deposits, all commercial banks, seasonally adjusted | AK2: Other deposits, all commercial banks, seasonally adjusted | AL2: Borrowings, all commercial banks, seasonally adjusted | AM2: Net due to related foreign offices, all commercial banks, seasonally adjusted | AN2: Other liabilities, all commercial banks, seasonally adjusted | AO2: Total liabilities, all commercial banks, seasonally adjusted | AP2: Residual (assets less liabilities), all commercial banks, seasonally adjusted | AQ2: Net unrealized gains (losses) on available-for-sale securities, all commercial banks, seasonally adjusted | AR2: U.S. Treasury and agency securities, MBS, all commercial banks, seasonally adjusted | AS2: Total Deposits
A3: Unit: | B3: Currency | C3: Currency | D3: Currency | E3: Currency | F3: Currency | G3: Currency | H3: Currency | I3: Currency | J3: Currency | K3: Currency | L3: Currency | M3: Currency | N3: Currency | O3: Currency | P3: Currency | Q3: Currency | R3: Currency | S3: Currency | T3: Currency | U3: Currency | V3: Currency | W3: Currency | X3: Currency | Y3: Currency | Z3: Currency | AA3: Currency | AB3: Currency | AC3: Currency | AD3: Currency | AE3: Currency | AF3: Currency | AG3: Currency | AH3: Currency | AI3: Currency | AJ3: Currency | AK3: Currency | AL3: Currency | AM3: Currency | AN3: Currency | AO3: Currency | AP3: Currency | AQ3: Currency | AR3: Currency
A4: Multiplier: | B4: 1000000 | C4: 1000000 | D4: 1000000 | E4: 1000000 | F4: 1000000 | G4: 1000000 | H4: 1000000 | I4: 1000000 | J4: 1000000 | K4: 1000000 | L4: 1000000 | M4: 1000000 | N4: 1000000 | O4: 1000000 | P4: 1000000 | Q4: 1000000 | R4: 1000000 | S4: 1000000 | T4: 1000000 | U4: 1000000 | V4: 1000000 | W4: 1000000 | X4: 1000000 | Y4: 1000000 | Z4: 1000000 | AA4: 1000000 | AB4: 1000000 | AC4: 1000000 | AD4: 1000000 | AE4: 1000000 | AF4: 1000000 | AG4: 1000000 | AH4: 1000000 | AI4: 1000000 | AJ4: 1000000 | AK4: 1000000 | AL4: 1000000 | AM4: 1000000 | AN4: 1000000 | AO4: 1000000 | AP4: 1000000 | AQ4: 1000000 | AR4: 1000000
A5: Currency: | B5: USD | C5: USD | D5: USD | E5: USD | F5: USD | G5: USD | H5: USD | I5: USD | J5: USD | K5: USD | L5: USD | M5: USD | N5: USD | O5: USD | P5: USD | Q5: USD | R5: USD | S5: USD | T5: USD | U5: USD | V5: USD | W5: USD | X5: USD | Y5: USD | Z5: USD | AA5: USD | AB5: USD | AC5: USD | AD5: USD | AE5: USD | AF5: USD | AG5: USD | AH5: USD | AI5: USD | AJ5: USD | AK5: USD | AL5: USD | AM5: USD | AN5: USD | AO5: USD | AP5: USD | AQ5: USD | AR5: USD
A6: Unique Identifier: | B6: H8/H8/B1001NCBAM | C6: H8/H8/B1002NCBAM | D6: H8/H8/B1003NCBAM | E6: H8/H8/B1301NCBAM | F6: H8/H8/B1302NCBAM | G6: H8/H8/B1011NCBAM | H6: H8/H8/B1303NCBAM | I6: H8/H8/B1304NCBAM | J6: H8/H8/B1020NCBAM | K6: H8/H8/B1023NCBAM | L6: H8/H8/B1026NCBAM | M6: H8/H8/B1221NCBAM | N6: H8/H8/B1027NCBAM | O6: H8/H8/B1220NCBAM | P6: H8/H8/B3219NCBAM | Q6: H8/H8/B1215NCBAM | R6: H8/H8/B1216NCBAM | S6: H8/H8/B1217NCBAM | T6: H8/H8/B1218NCBAM | U6: H8/H8/B1029NCBAM | V6: H8/H8/B1247NCBAM | W6: H8/H8/B3248NCBAM | X6: H8/H8/B1243NCBAM | Y6: H8/H8/B1245NCBAM | Z6: H8/H8/B3305NCBAM | AA6: H8/H8/B1030NCBAM | AB6: H8/H8/B1310NCBAM | AC6: H8/H8/B1043NCBAM | AD6: H8/H8/B1048NCBAM | AE6: H8/H8/B3092NCBAM | AF6: H8/H8/B1047NCBAM | AG6: H8/H8/B3053NCBAM | AH6: H8/H8/B1151NCBAM | AI6: H8/H8/B1058NCBAM | AJ6: H8/H8/B1072NCBAM | AK6: H8/H8/B1110NCBAM | AL6: H8/H8/B3094NCBAM | AM6: H8/H8/B1100NCBAM | AN6: H8/H8/B3095NCBAM | AO6: H8/H8/B1152NCBAM | AP6: H8/H8/B1091NCBAM | AQ6: H8/H8/B1231NCBAM | AR6: H8/H8/B8321NCBAM
A7: Time Period | B7: B1001NCBAM | C7: B1002NCBAM | D7: B1003NCBAM | E7: B1301NCBAM | F7: B1302NCBAM | G7: B1011NCBAM | H7: B1303NCBAM | I7: B1304NCBAM | J7: B1020NCBAM | K7: B1023NCBAM | L7: B1026NCBAM | M7: B1221NCBAM | N7: B1027NCBAM | O7: B1220NCBAM | P7: B3219NCBAM | Q7: B1215NCBAM | R7: B1216NCBAM | S7: B1217NCBAM | T7: B1218NCBAM | U7: B1029NCBAM | V7: B1247NCBAM | W7: B3248NCBAM | X7: B1243NCBAM | Y7: B1245NCBAM | Z7: B3305NCBAM | AA7: B1030NCBAM | AB7: B1310NCBAM | AC7: B1043NCBAM | AD7: B1048NCBAM | AE7: B3092NCBAM | AF7: B1047NCBAM | AG7: B3053NCBAM | AH7: B1151NCBAM | AI7: B1058NCBAM | AJ7: B1072NCBAM | AK7: B1110NCBAM | AL7: B3094NCBAM | AM7: B1100NCBAM | AN7: B3095NCBAM | AO7: B1152NCBAM | AP7: B1091NCBAM | AQ7: B1231NCBAM | AR7: B8321NCBAM
A8: 1947-01 | B8: 109116.7 | C8: 82379.3 | D8: 74124.7 | G8: 8254.5 | J8: 26737.5 | K8: 11289.4 | L8: 6796 | U8: 4161.2
A9: 1947-02 | B9: 108530.3 | C9: 81273.4 | D9: 73208 | G9: 8065.4 | J9: 27257 | K9: 11517.9 | L9: 6955.1 | U9: 4296.6
A10: 1947-03 | B10: 108370.6 | C10: 80565.3 | D10: 72498.3 | G10: 8067 | J10: 27805.4 | K10: 11766.7 | L10: 7124.9 | U10: 4430.6
A11: 1947-04 | B11: 108560.8 | C11: 80189.4 | D11: 72226.4 | G11: 7962.9 | J11: 28371.4 | K11: 12026.9 | L11: 7296.6 | U11: 4568.7
A12: 1947-05 | B12: 108539 | C12: 79606.7 | D12: 71902.1 | G12: 7704.6 | J12: 28932.2 | K12: 12278.8 | L12: 7469.9 | U12: 4708.7
A13: 1947-06 | B13: 108459.4 | C13: 78854.3 | D13: 71414 | G13: 7440.4 | J13: 29605 | K13: 12483.2 | L13: 7636.1 | U13: 4846.5
A14: 1947-07 | B14: 108747.5 | C14: 77749.5 | D14: 71104.8 | G14: 6644.7 | J14: 30998 | K14: 12780 | L14: 7809.2 | U14: 4981.5
A15: 1947-08 | B15: 109045.3 | C15: 77544.9 | D15: 70835.5 | G15: 6709.5 | J15: 31500.4 | K15: 13082.2 | L15: 7980.9 | U15: 5116.8
A16: 1947-09 | B16: 109921.9 | C16: 77952.7 | D16: 71156.5 | G16: 6796.1 | J16: 31969.2 | K16: 13352.3 | L16: 8148.7 | U16: 5248.4
A17: 1947-10 | B17: 110375.5 | C17: 77936.5 | D17: 71101.5 | G17: 6835 | J17: 32439 | K17: 13628.7 | L17: 8317.4 | U17: 5381.9
A18: 1947-11 | B18: 110432.6 | C18: 77541.6 | D18: 70724.6 | G18: 6817 | J18: 32891.1 | K18: 13899.8 | L18: 8484.5 | U18: 5514.2
A19: 1947-12 | B19: 110296.7 | C19: 76921.3 | D19: 70083.3 | G19: 6837.9 | J19: 33375.4 | K19: 14205.3 | L19: 8642.8 | U19: 5645.6
... A319: 1972-12 | B319: 560125.1 | C319: 159746.8 | D319: 86939.3 | G319: 72807.5 | J319: 400378.3 | K319: 133109.3 | L319: 96869.5 | U319: 85260.1
A320: 1973-01 | B320: 566513.4 | C320: 161359.5 | D320: 89971.8 | G320: 71387.7 | J320: 405153.9 | K320: 135413.5 | L320: 98701.1 | U320: 86477.4 | Z320: 84561.9 | AD320: 84468.7 | AF320: 3621.2 | AG320: 29552.4 | AH320: 702318.8 | AI320: 596878.7 | AJ320: 94393.3 | AL320: 7546.4 | AN320: 21037.2 | AO320: 626069.9 | AP320: 76248.9 | AS320: =SUM(AI320:AK320) -> 691272 | AT320: =AH320/AS320 -> 1.0159804
A321: 1973-02 | B321: 574254.8 | C321: 158635.2 | D321: 86578.8 | G321: 72056.5 | J321: 415619.6 | K321: 140798.3 | L321: 100456.1 | U321: 88258.7 | Z321: 86106.5 | AD321: 83623.6 | AF321: 3950.2 | AG321: 30689.6 | AH321: 710763.2 | AI321: 598920.7 | AJ321: 97452.2 | AL321: 9121.3 | AN321: 21832.7 | AO321: 629659.8 | AP321: 81103.4 | AS321: =SUM(AI321:AK321) -> 696372.9 | AT321: =AH321/AS321 -> 1.0206646
A322: 1973-03 | B322: 584043.9 | C322: 158098.1 | D322: 85320.9 | G322: 72777.2 | J322: 425945.8 | K322: 144957.6 | L322: 102460.6 | U322: 89855.5 | Z322: 88672.2 | AD322: 81888.4 | AF322: 4321.4 | AG322: 31653.3 | AH322: 719914 | AI322: 602988.9 | AJ322: 101766.9 | AL322: 10524.6 | AN322: 22585.4 | AO322: 635251.7 | AP322: 84662.2 | AS322: =SUM(AI322:AK322) -> 704755.8 | AT322: =AH322/AS322 -> 1.0215084
A323: 1973-04 | B323: 590109 | C323: 158342.5 | D323: 85348.2 | G323: 72994.2 | J323: 431766.5 | K323: 147534.3 | L323: 104303.2 | U323: 91127.8 | Z323: 88801.3 | AD323: 83097.8 | AF323: 4343.4 | AG323: 32503 | AH323: 728455.9 | AI323: 612431.7 | AJ323: 104024.9 | AL323: 10693.7 | AN323: 23314 | AO323: 645630.4 | AP323: 82825.5 | AS323: =SUM(AI323:AK323) -> 716456.6 | AT323: =AH323/AS323 -> 1.0167481
A324: 1973-05 | B324: 595891.1 | C324: 157084.2 | D324: 83157 | G324: 73927.2 | J324: 438806.8 | K324: 149965.9 | L324: 105816.3 | U324: 92158.8 | Z324: 90865.8 | AD324: 84324.9 | AF324: 4809.6 | AG324: 32864.4 | AH324: 737316.4 | AI324: 614374.1 | AJ324: 106421.6 | AL324: 11464.4 | AN324: 24319.9 | AO324: 649692.4 | AP324: 87624 | AS324: =SUM(AI324:AK324) -> 720795.7 | AT324: =AH324/AS324 -> 1.0229201
A325: 1973-06 | B325: 603759 | C325: 157686.5 | D325: 83142.7 | G325: 74543.7 | J325: 446072.6 | K325: 152829.2 | L325: 107511.3 | U325: 93248.6 | Z325: 92483.4 | AD325: 85793.4 | AF325: 5083.6 | AG325: 33553.4 | AH325: 748128 | AI325: 623141.1 | AJ325: 107138.9 | AL325: 12303.6 | AN325: 24523.7 | AO325: 659303.2 | AP325: 88824.8 | AS325: =SUM(AI325:AK325) -> 730280 | AT325: =AH325/AS325 -> 1.0244399
A326: 1973-07 | B326: 610141.6 | C326: 157329.7 | D326: 82198.5 | G326: 75131.2 | J326: 452811.9 | K326: 155329.1 | L326: 109238.7 | U326: 94325.2 | Z326: 93918.9 | AD326: 88236.9 | AF326: 5374.3 | AG326: 33806.1 | AH326: 758057.8 | AI326: 630928.1 | AJ326: 109100.7 | AL326: 13618.1 | AN326: 24269.9 | AO326: 667897.9 | AP326: 90159.9 | AS326: =SUM(AI326:AK326) -> 740028.8 | AT326: =AH326/AS326 -> 1.0243626
A327: 1973-08 | B327: 616517.2 | C327: 157733.2 | D327: 81396.5 | G327: 76336.7 | J327: 458784 | K327: 158068.1 | L327: 110902.4 | U327: 95283.3 | Z327: 94530.2 | AD327: 86650.1 | AF327: 5240 | AG327: 35037.3 | AH327: 764744.3 | AI327: 629977.3 | AJ327: 113785.8 | AL327: 14378.5 | AN327: 25014.7 | AO327: 668182 | AP327: 96562.3 | AS327: =SUM(AI327:AK327) -> 743763.1 | AT327: =AH327/AS327 -> 1.0282095
A328: 1973-09 | B328: 621387 | C328: 159393.2 | D328: 82381.2 | G328: 77012 | J328: 461993.8 | K328: 158506.6 | L328: 112484.8 | U328: 96007.2 | Z328: 94995.2 | AD328: 88681.5 | AF328: 5114.6 | AG328: 35474.1 | AH328: 771226.5 | AI328: 638646.4 | AJ328: 115221 | AL328: 14515.2 | AN328: 24948 | AO328: 676638.4 | AP328: 94588.1 | AS328: =SUM(AI328:AK328) -> 753867.4 | AT328: =AH328/AS328 -> 1.0230267
A329: 1973-10 | B329: 625568.1 | C329: 161086.2 | D329: 83565.1 | G329: 77521.1 | J329: 464481.9 | K329: 159169.4 | L329: 113968.4 | U329: 96788.9 | Z329: 94555.3 | AD329: 91244 | AF329: 5281.7 | AG329: 36207.8 | AH329: 780241.8 | AI329: 647617.9 | AJ329: 115092.4 | AL329: 14398.6 | AN329: 25140.9 | AO329: 685556.2 | AP329: 94685.6 | AS329: =SUM(AI329:AK329) -> 762710.3 | AT329: =AH329/AS329 -> 1.0229858
A330: 1973-11 | B330: 631539.8 | C330: 164213.8 | D330: 87719.5 | G330: 76494.2 | J330: 467326 | K330: 159935.3 | L330: 115531.3 | U330: 97775.8 | Z330: 94083.6 | AD330: 92072 | AF330: 5644.1 | AG330: 36148.4 | AH330: 787258.3 | AI330: 649140.6 | AJ330: 113958.4 | AL330: 14423.7 | AN330: 26196.7 | AO330: 688511.1 | AP330: 98747.2 | AS330: =SUM(AI330:AK330) -> 763099 | AT330: =AH330/AS330 -> 1.0316595
A331: 1973-12 | B331: 641131.5 | C331: 166904.5 | D331: 90078.2 | G331: 76826.2 | J331: 474227 | K331: 161211.3 | L331: 117002 | U331: 98350.7 | Z331: 97663.1 | AD331: 91904.9 | AF331: 5631.9 | AG331: 36616.8 | AH331: 798083.8 | AI331: 663699.3 | AJ331: 115016.2 | AL331: 14896.6 | AN331: 26343.1 | AO331: 703335 | AP331: 94748.7 | AS331: =SUM(AI331:AK331) -> 778715.5 | AT331: =AH331/AS331 -> 1.0248721
... A493: 1987-06 | B493: 2128263.7 | C493: 512794.9 | D493: 319570.8 | G493: 193224.1 | J493: 1615468.8 | K493: 554536.4 | L493: 541734.6 | U493: 315461 | Z493: 203736.8 | AD493: 239098.2 | AF493: 46455.6 | AG493: 154025.4 | AH493: 2679452.5 | AI493: 1956094.5 | AJ493: 374940.2 | AL493: 400781.4 | AN493: 150118.6 | AO493: 2496445.3 | AP493: 183007.2 | AS493: =SUM(AI493:AK493) -> 2331034.7 | AT493: =AH493/AS493 -> 1.1494692
A494: 1987-07 | B494: 2134064.1 | C494: 514631 | D494: 322413.1 | G494: 192217.9 | J494: 1619433.1 | K494: 553429.3 | L494: 549405 | N494: 24996.2 | U494: 316961.3 | Z494: 199637.5 | AD494: 232366.3 | AF494: 46905.2 | AG494: 156180.7 | AH494: 2675367.4 | AI494: 1955520.6 | AJ494: 376907.5 | AL494: 400944.6 | AN494: 146504.1 | AO494: 2496579.9 | AP494: 178787.5 | AS494: =SUM(AI494:AK494) -> 2332428.1 | AT494: =AH494/AS494 -> 1.147031
A495: 1987-08 | B495: 2145622.3 | C495: 517365 | D495: 326585.4 | G495: 190779.7 | J495: 1628257.3 | K495: 554134.1 | L495: 556232.1 | N495: 26179 | U495: 319344.3 | Z495: 198546.8 | AD495: 234014.5 | AF495: 44887 | AG495: 157279.8 | AH495: 2691966.6 | AI495: 1961994.3 | AJ495: 377261.6 | AL495: 406575.1 | AN495: 145977.2 | AO495: 2514874.4 | AP495: 177092.3 | AS495: =SUM(AI495:AK495) -> 2339255.9 | AT495: =AH495/AS495 -> 1.150779
A496: 1987-09 | B496: 2168390.3 | C496: 520434.8 | D496: 329523.6 | G496: 190911.2 | J496: 1647955.5 | K496: 561315.8 | L496: 563145.4 | N496: 27441.6 | U496: 321890.1 | Z496: 201604.3 | AD496: 235208.6 | AF496: 45121.5 | AG496: 161969.4 | AH496: 2720042.6 | AI496: 1967775.6 | AJ496: 378173.9 | AL496: 405264.6 | AN496: 149489.4 | AO496: 2534488.5 | AP496: 185554.1 | AS496: =SUM(AI496:AK496) -> 2345949.5 | AT496: =AH496/AS496 -> 1.1594634
A497: 1987-10 | B497: 2181092.1 | C497: 519795.9 | D497: 329945.4 | G497: 189850.5 | J497: 1661296.2 | K497: 563135.2 | L497: 570786.1 | N497: 28478.9 | U497: 324308.8 | Z497: 203066.1 | AD497: 233999.9 | AF497: 45307.2 | AG497: 165501.1 | AH497: 2742921.4 | AI497: 1980899.9 | AJ497: 385908.6 | AL497: 410041.8 | AN497: 155010.1 | AO497: 2554330.5 | AP497: 188591 | AS497: =SUM(AI497:AK497) -> 2366808.5 | AT497: =AH497/AS497 -> 1.1589114
A498: 1987-11 | B498: 2184679.4 | C498: 521498 | D498: 331409.5 | G498: 190088.5 | J498: 1663181.3 | K498: 562499.9 | L498: 577697.8 | N498: 29577.2 | U498: 325035.2 | Z498: 197948.5 | AD498: 230357.7 | AF498: 45251 | AG498: 164366.3 | AH498: 2733486 | AI498: 1984034.6 | AJ498: 392363.3 | AL498: 409656.4 | AN498: 152460.8 | AO498: 2552006.7 | AP498: 181479.3 | AS498: =SUM(AI498:AK498) -> 2376397.9 | AT498: =AH498/AS498 -> 1.1502644
A499: 1987-12 | B499: 2198307.5 | C499: 525111.3 | D499: 335150.1 | G499: 189961.2 | J499: 1673196.2 | K499: 564982.8 | L499: 585701.5 | N499: 30624.4 | U499: 326865.4 | Z499: 195646.5 | AD499: 228877.7 | AF499: 44573.3 | AG499: 160188.6 | AH499: 2734023.8 | AI499: 1985596.9 | AJ499: 394750.9 | AL499: 408635.6 | AN499: 151938.9 | AO499: 2555242.6 | AP499: 178781.2 | AS499: =SUM(AI499:AK499) -> 2380347.8 | AT499: =AH499/AS499 -> 1.1485816
A500: 1988-01 | B500: 2212630 | C500: 527214.5 | D500: 335251.9 | G500: 191962.6 | J500: 1685415.5 | K500: 567074.6 | L500: 591581 | N500: 31826.6 | U500: 330265.8 | Z500: 196494.2 | AD500: 234979 | AF500: 44104.5 | AG500: 154988.2 | AH500: 2751583.2 | AI500: 2000534.2 | AJ500: 397004.7 | AL500: 417718.3 | AN500: 149398.7 | AO500: 2575012.3 | AP500: 176570.9 | AS500: =SUM(AI500:AK500) -> 2397538.9 | AT500: =AH500/AS500 -> 1.1476699
A501: 1988-02 | B501: 2221846.6 | C501: 527414.9 | D501: 335678.2 | G501: 191736.8 | J501: 1694431.7 | K501: 568290.4 | L501: 595947.9 | N501: 32466.2 | U501: 332407.7 | Z501: 197785.8 | AD501: 235310.3 | AF501: 45148 | AG501: 156852.8 | AH501: 2763919.4 | AI501: 2007374.4 | AJ501: 398940.3 | AL501: 421772.1 | AN501: 149029.3 | AO501: 2579899.8 | AP501: 184019.6 | AS501: =SUM(AI501:AK501) -> 2406314.7 | AT501: =AH501/AS501 -> 1.1486109
A502: 1988-03 | B502: 2238934.5 | C502: 531375.3 | D502: 336796.1 | G502: 194579.2 | J502: 1707559.3 | K502: 571402.5 | L502: 601449.3 | N502: 33015.8 | U502: 336318.9 | Z502: 198388.6 | AD502: 232658.7 | AF502: 45366.9 | AG502: 156636.5 | AH502: 2776668.7 | AI502: 2016215.1 | AJ502: 400284.3 | AL502: 434030.8 | AN502: 147577.3 | AO502: 2594451 | AP502: 182217.7 | AS502: =SUM(AI502:AK502) -> 2416499.4 | AT502: =AH502/AS502 -> 1.1490459
A503: 1988-04 | B503: 2259440.8 | C503: 536700.3 | D503: 341647.2 | G503: 195053.1 | J503: 1722740.5 | K503: 577393.3 | L503: 608896.4 | N503: 33816.3 | U503: 339485.7 | Z503: 196965.1 | AD503: 233698.6 | AF503: 46092.5 | AG503: 157458.5 | AH503: 2805335.1 | AI503: 2027994.9 | AJ503: 400510.7 | AL503: 444206 | AN503: 147631.4 | AO503: 2619887 | AP503: 185448.1 | AS503: =SUM(AI503:AK503) -> 2428505.6 | AT503: =AH503/AS503 -> 1.1551693
A504: 1988-05 | B504: 2279613.6 | C504: 540185.8 | D504: 344727.8 | G504: 195458 | J504: 1739427.8 | K504: 583826.2 | L504: 616129.2 | N504: 34622.9 | U504: 341228.1 | Z504: 198244.2 | AD504: 238473.7 | AF504: 44906.7 | AG504: 160516 | AH504: 2833320 | AI504: 2047897.7 | AJ504: 402114.4 | AL504: 447477.7 | AN504: 150541.4 | AO504: 2648661.9 | AP504: 184658.1 | AS504: =SUM(AI504:AK504) -> 2450012.1 | AT504: =AH504/AS504 -> 1.1564514
A505: 1988-06 | B505: 2298769.6 | C505: 545129.3 | D505: 349945.8 | G505: 195183.6 | J505: 1753640.3 | K505: 589003.3 | L505: 622781.4 | N505: 35403.6 | U505: 343354.2 | Z505: 198501.4 | AD505: 239767.7 | AF505: 45769 | AG505: 162573.7 | AH505: 2860290.4 | AI505: 2060085.4 | AJ505: 405458.7 | AL505: 454089.4 | AN505: 154589.4 | AO505: 2670844.4 | AP505: 189446 | AS505: =SUM(AI505:AK505) -> 2465544.1 | AT505: =AH505/AS505 -> 1.1601051
... A649: 2000-06 | B649: 4745059.8 | C649: 1169600.8 | D649: 819472.6 | G649: 350128.1 | J649: 3575459 | K649: 1062770.4 | L649: 1585383.4 | N649: 114671.8 | U649: 529536.1 | Z649: 397769.1 | AD649: 289346.6 | AF649: 80095.4 | AG649: 521956.6 | AH649: 5871483.8 | AI649: 3595943.3 | AJ649: 879866.3 | AL649: 1410329.3 | AN649: 432004.4 | AO649: 5637417.5 | AP649: 234066.2 | AS649: =SUM(AI649:AK649) -> 4475809.6 | AT649: =AH649/AS649 -> 1.3118261
A650: 2000-07 | B650: 4777238 | C650: 1178015.4 | D650: 819907.8 | G650: 358107.5 | J650: 3599222.6 | K650: 1068573.7 | L650: 1600642.3 | N650: 118462.8 | U650: 531142 | V650: 211897.8 | W650: 319244.2 | Z650: 398864.5 | AD650: 286711.3 | AF650: 87604.1 | AG650: 515885.1 | AH650: 5905081.8 | AI650: 3626297.3 | AJ650: 895407.2 | AL650: 1426429.5 | AN650: 425923.5 | AO650: 5678886 | AP650: 226195.8 | AS650: =SUM(AI650:AK650) -> 4521704.5 | AT650: =AH650/AS650 -> 1.3059416
A651: 2000-08 | B651: 4803014 | C651: 1176437.4 | D651: 811020.5 | G651: 365417 | J651: 3626576.5 | K651: 1071687.8 | L651: 1613806.5 | N651: 120109.6 | U651: 538855.4 | V651: 217854 | W651: 321001.4 | Z651: 402226.9 | AD651: 285118.8 | AF651: 91492 | AG651: 519848.1 | AH651: 5934153.2 | AI651: 3652747.6 | AJ651: 911559.1 | AL651: 1424906.7 | AN651: 434214.5 | AO651: 5714051.1 | AP651: 220102.2 | AS651: =SUM(AI651:AK651) -> 4564306.7 | AT651: =AH651/AS651 -> 1.3001215
A652: 2000-09 | B652: 4825515.8 | C652: 1181439.3 | D652: 806795.7 | G652: 374643.6 | J652: 3644076.5 | K652: 1072962.7 | L652: 1624415.4 | N652: 121939.5 | U652: 543717.1 | V652: 222410.9 | W652: 321306.3 | Z652: 402981.3 | AD652: 279831.3 | AF652: 90039.2 | AG652: 538170 | AH652: 5973716.5 | AI652: 3668253.4 | AJ652: 910051 | AL652: 1419638.6 | AN652: 447335.6 | AO652: 5736376.6 | AP652: 237339.8 | AS652: =SUM(AI652:AK652) -> 4578304.4 | AT652: =AH652/AS652 -> 1.304788
A653: 2000-10 | B653: 4818311.2 | C653: 1165916.6 | D653: 796335.8 | G653: 369580.7 | J653: 3652394.6 | K653: 1077970.4 | L653: 1625104.6 | N653: 123707 | U653: 544271.9 | V653: 220752.4 | W653: 323519.5 | Z653: 405047.7 | AD653: 282244.9 | AF653: 91958 | AG653: 548885.7 | AH653: 5990969.9 | AI653: 3679276.5 | AJ653: 905890.8 | AL653: 1404702.8 | AN653: 439474.5 | AO653: 5730192.1 | AP653: 260777.8 | AS653: =SUM(AI653:AK653) -> 4585167.3 | AT653: =AH653/AS653 -> 1.3065979
A654: 2000-11 | B654: 4832511.3 | C654: 1161836.6 | D654: 786996 | G654: 374840.6 | J654: 3670674.7 | K654: 1080495.2 | L654: 1634706.8 | N654: 125926.8 | U654: 548263.8 | V654: 222338.7 | W654: 325925.1 | Z654: 407208.9 | AD654: 272173.4 | AF654: 92526.2 | AG654: 540377.3 | AH654: 5990639.3 | AI654: 3670462.4 | AJ654: 906168.1 | AL654: 1396500.4 | AN654: 442459.3 | AO654: 5716039.2 | AP654: 274600.1 | AS654: =SUM(AI654:AK654) -> 4576630.5 | AT654: =AH654/AS654 -> 1.3089628
A655: 2000-12 | B655: 4866156.7 | C655: 1175824.4 | D655: 789645.2 | G655: 386179.2 | J655: 3690332.3 | K655: 1085298.2 | L655: 1638747.8 | N655: 127963.3 | U655: 555531.4 | V655: 228197.3 | W655: 327334.1 | Z655: 410755 | AD655: 284336.3 | AF655: 91657.3 | AG655: 556091.3 | AH655: 6067535.8 | AI655: 3724070.7 | AJ655: 922511.8 | AL655: 1434993.6 | AN655: 452383.4 | AO655: 5809431.8 | AP655: 258103.9 | AS655: =SUM(AI655:AK655) -> 4646582.5 | AT655: =AH655/AS655 -> 1.3058061
A656: 2001-01 | B656: 4900291.2 | C656: 1191540.7 | D656: 791748.8 | G656: 399791.8 | J656: 3708750.5 | K656: 1094094.2 | L656: 1641718.4 | N656: 128653.5 | U656: 558590.1 | V656: 230967.4 | W656: 327622.7 | Z656: 414347.8 | AD656: 294279.3 | AF656: 94171 | AG656: 578185.6 | AH656: 6151019.1 | AI656: 3757823.8 | AJ656: 930598.1 | AL656: 1468114.2 | AN656: 473643.3 | AO656: 5877247 | AP656: 273772.2 | AS656: =SUM(AI656:AK656) -> 4688421.9 | AT656: =AH656/AS656 -> 1.3119594
A657: 2001-02 | B657: 4903947.2 | C657: 1181788.5 | D657: 779036.4 | G657: 402752.1 | J657: 3722158.7 | K657: 1094338.1 | L657: 1654788.7 | N657: 130605.7 | U657: 557858 | V657: 229551.1 | W657: 328306.9 | Z657: 415173.9 | AD657: 280046.5 | AF657: 94384.7 | AG657: 574179.4 | AH657: 6137968.4 | AI657: 3773843.3 | AJ657: 926593 | AL657: 1463301.6 | AN657: 474153 | AO657: 5870782.7 | AP657: 267185.7 | AS657: =SUM(AI657:AK657) -> 4700436.3 | AT657: =AH657/AS657 -> 1.3058295
A658: 2001-03 | B658: 4912199.7 | C658: 1178407.9 | D658: 767414.1 | G658: 410993.8 | J658: 3733791.8 | K658: 1091987.7 | L658: 1668379.5 | N658: 132024.3 | U658: 557205.5 | V658: 228144.8 | W658: 329060.6 | Z658: 416219.2 | AD658: 279177.5 | AF658: 93021.2 | AG658: 601100.8 | AH658: 6188791.5 | AI658: 3804924 | AJ658: 932149.4 | AL658: 1465086.6 | AN658: 496426.4 | AO658: 5919212.6 | AP658: 269578.9 | AS658: =SUM(AI658:AK658) -> 4737073.4 | AT658: =AH658/AS658 -> 1.3064589
A659: 2001-04 | B659: 4932370.4 | C659: 1184111.1 | D659: 768937.7 | G659: 415173.4 | J659: 3748259.2 | K659: 1089163.6 | L659: 1682457 | N659: 133027.3 | U659: 561350.2 | V659: 232200.8 | W659: 329149.4 | Z659: 415288.4 | AD659: 278363.1 | AF659: 93971.5 | AG659: 607461.8 | AH659: 6229042.7 | AI659: 3843682.6 | AJ659: 939485.7 | AL659: 1483196.1 | AN659: 496657.1 | AO659: 5948783.7 | AP659: 280259 | AS659: =SUM(AI659:AK659) -> 4783168.3 | AT659: =AH659/AS659 -> 1.3022838
A660: 2001-05 | B660: 4953279.7 | C660: 1192847.1 | D660: 771057.8 | G660: 421789.3 | J660: 3760432.6 | K660: 1084145.7 | L660: 1695265.6 | N660: 135112.1 | U660: 566114.6 | V660: 235574.1 | W660: 330540.5 | Z660: 414906.6 | AD660: 277078.2 | AF660: 90243.2 | AG660: 598466.1 | AH660: 6219285.4 | AI660: 3868076.4 | AJ660: 946589 | AL660: 1453394.8 | AN660: 496367.1 | AO660: 5946266.5 | AP660: 273018.8 | AS660: =SUM(AI660:AK660) -> 4814665.4 | AT660: =AH660/AS660 -> 1.2917378
A661: 2001-06 | B661: 4951726.3 | C661: 1201595.9 | D661: 771163.3 | G661: 430432.6 | J661: 3750130.5 | K661: 1072034.5 | L661: 1700033.7 | N661: 136185.2 | U661: 564557.4 | V661: 233267.1 | W661: 331290.3 | Z661: 413504.8 | AD661: 272266.3 | AF661: 87646.2 | AG661: 598723.1 | AH661: 6207554.6 | AI661: 3882781.4 | AJ661: 950865.7 | AL661: 1433649.4 | AN661: 496091 | AO661: 5932611.4 | AP661: 274943.2 | AS661: =SUM(AI661:AK661) -> 4833647.1 | AT661: =AH661/AS661 -> 1.2842383
... A696: 2004-05 | B696: 6066598.4 | C696: 1694588.1 | D696: 1178672.5 | G696: 515915.7 | J696: 4372010.3 | K696: 862844.8 | L696: 2383958.1 | N696: 327467.9 | U696: 677176.8 | V696: 284903.9 | W696: 392272.9 | Z696: 448030.6 | AD696: 330834.3 | AF696: 122286.5 | AG696: 794850.3 | AH696: 7664792.3 | AI696: 4907152.6 | AJ696: 1093517.1 | AL696: 1780597.2 | AN696: 537641.8 | AO696: 7233687.2 | AP696: 431105.1 | AS696: =SUM(AI696:AK696) -> 6000669.7 | AT696: =AH696/AS696 -> 1.2773228
A697: 2004-06 | B697: 6107703.2 | C697: 1701937.1 | D697: 1180685.8 | G697: 521251.3 | J697: 4405766.1 | K697: 869158.5 | L697: 2409802.7 | M697: 1406891.5 | N697: 336426.2 | O697: 1070465.4 | P697: 1002911.2 | U697: 679977.5 | V697: 287433.6 | W697: 392543.9 | Z697: 446827.4 | AD697: 328942.5 | AF697: 123608.9 | AG697: 803398.1 | AH697: 7742339 | AI697: 4940621.4 | AJ697: 1119960.1 | AL697: 1826101.2 | AM697: 44479.5 | AN697: 520342.1 | AO697: 7331544.1 | AP697: 410794.9 | AS697: =SUM(AI697:AK697) -> 6060581.5 | AT697: =AH697/AS697 -> 1.2774911
A698: 2004-07 | B698: 6135178.5 | C698: 1702420 | D698: 1179549.9 | G698: 522870.1 | J698: 4432758.5 | K698: 878132.3 | L698: 2413656 | M698: 1400378.7 | N698: 345451.6 | O698: 1054927.1 | P698: 1013277.2 | U698: 680087 | V698: 287878.6 | W698: 392208.4 | Z698: 460883.1 | AD698: 326447.4 | AF698: 129698 | AG698: 829761.6 | AH698: 7845745.7 | AI698: 4991184.8 | AJ698: 1165780.5 | AL698: 1863073.3 | AM698: 31769.2 | AN698: 547341.5 | AO698: 7433368.8 | AP698: 412376.9 | AS698: =SUM(AI698:AK698) -> 6156965.3 | AT698: =AH698/AS698 -> 1.2742878
A699: 2004-08 | B699: 6169835.6 | C699: 1705019.5 | D699: 1179525.4 | G699: 525494.1 | J699: 4464816.1 | K699: 883042.4 | L699: 2437303.6 | M699: 1411114.4 | N699: 357132.7 | O699: 1053981.7 | P699: 1026189.2 | U699: 683613.5 | V699: 290661.3 | W699: 392952.2 | Z699: 460856.7 | AD699: 323509.7 | AF699: 125962.1 | AG699: 845166.2 | AH699: 7877132.4 | AI699: 5010058.4 | AJ699: 1158995.4 | AL699: 1838850.5 | AM699: 36321.4 | AN699: 560140.6 | AO699: 7445370.8 | AP699: 431761.6 | AS699: =SUM(AI699:AK699) -> 6169053.8 | AT699: =AH699/AS699 -> 1.2768785
A700: 2004-09 | B700: 6230151.9 | C700: 1723268.3 | D700: 1178549.1 | G700: 544719.1 | J700: 4506883.7 | K700: 886831.5 | L700: 2466440.9 | M700: 1426620.2 | N700: 368796 | O700: 1057824.2 | P700: 1039820.6 | U700: 686419.5 | V700: 294299.2 | W700: 392120.3 | Z700: 467191.8 | AD700: 322236.8 | AF700: 121820.3 | AG700: 860277.9 | AH700: 7960883.3 | AI700: 5042920.7 | AJ700: 1159532.1 | AL700: 1855448.7 | AM700: 33784.9 | AN700: 566035 | AO700: 7498189.3 | AP700: 462694 | AS700: =SUM(AI700:AK700) -> 6202452.8 | AT700: =AH700/AS700 -> 1.2835057
A701: 2004-10 | B701: 6260154.4 | C701: 1720985.2 | D701: 1161295.7 | G701: 559689.5 | J701: 4539169.2 | K701: 889304.4 | L701: 2495946.7 | M701: 1443062.4 | N701: 381560.9 | O701: 1061501.5 | P701: 1052884.3 | U701: 684346.8 | V701: 291309 | W701: 393037.8 | Z701: 469571.4 | AD701: 320300.2 | AF701: 125201.7 | AG701: 860879.1 | AH701: 7973739.6 | AI701: 5073483.7 | AJ701: 1167821.9 | AL701: 1855242.1 | AM701: 16490.3 | AN701: 548033 | AO701: 7493249 | AP701: 480490.6 | AS701: =SUM(AI701:AK701) -> 6241305.6 | AT701: =AH701/AS701 -> 1.2775756
A702: 2004-11 | B702: 6301976.9 | C702: 1720611.4 | D702: 1156089.9 | G702: 564521.5 | J702: 4581365.5 | K702: 897653 | L702: 2526237.7 | M702: 1458948.4 | N702: 389432.9 | O702: 1069515.5 | P702: 1067289.2 | U702: 680706.3 | V702: 287768.8 | W702: 392937.6 | Z702: 476768.5 | AD702: 319709.3 | AF702: 106455.2 | AG702: 867384.6 | AH702: 8009666.5 | AI702: 5127547.8 | AJ702: 1185593.6 | AL702: 1840779.5 | AM702: -464 | AN702: 569916.2 | AO702: 7537779.5 | AP702: 471887 | AS702: =SUM(AI702:AK702) -> 6313141.4 | AT702: =AH702/AS702 -> 1.2687291
A703: 2004-12 | B703: 6373479.9 | C703: 1745214.3 | D703: 1172261.9 | G703: 572952.4 | J703: 4628265.6 | K703: 906435.4 | L703: 2552724.8 | M703: 1472880.9 | N703: 395357.6 | O703: 1077523.4 | P703: 1079843.9 | U703: 691415 | V703: 296868.7 | W703: 394546.3 | Z703: 477690.4 | AD703: 314041.8 | AF703: 82163.7 | AG703: 879955.5 | AH703: 8038937.8 | AI703: 5155032.3 | AJ703: 1203117.4 | AL703: 1813118 | AM703: -3363.9 | AN703: 583866.8 | AO703: 7548653.1 | AP703: 490284.7 | AS703: =SUM(AI703:AK703) -> 6358149.7 | AT703: =AH703/AS703 -> 1.2643518
A704: 2005-01 | B704: 6492188.1 | C704: 1812000.4 | D704: 1193501.6 | G704: 618498.8 | J704: 4680187.6 | K704: 921448.5 | L704: 2576173.6 | M704: 1481424.6 | N704: 402563.8 | O704: 1078860.7 | P704: 1094749 | U704: 693794.9 | V704: 303790.4 | W704: 390004.5 | Z704: 488770.7 | AD704: 317534.5 | AF704: 69718.7 | AG704: 862463.4 | AH704: 8095843.1 | AI704: 5193577.2 | AJ704: 1231317.2 | AL704: 1810359.9 | AM704: 24575.7 | AN704: 579083.6 | AO704: 7607596.5 | AP704: 488246.6 | AS704: =SUM(AI704:AK704) -> 6424894.4 | AT704: =AH704/AS704 -> 1.2600741
A705: 2005-02 | B705: 6555585.7 | C705: 1838076.7 | D705: 1209980 | G705: 628096.7 | J705: 4717509 | K705: 931850.6 | L705: 2605761.6 | M705: 1499025.2 | N705: 408308 | O705: 1090717.2 | P705: 1106736.4 | U705: 690746.4 | V705: 299128.9 | W705: 391617.4 | Z705: 489150.4 | AD705: 313802.6 | AF705: 74841.3 | AG705: 857963.7 | AH705: 8174029.5 | AI705: 5222570.4 | AJ705: 1239618.4 | AL705: 1820372.6 | AM705: 32981.6 | AN705: 585989.3 | AO705: 7661914 | AP705: 512115.5 | AS705: =SUM(AI705:AK705) -> 6462188.8 | AT705: =AH705/AS705 -> 1.2649011
A706: 2005-03 | B706: 6625808.8 | C706: 1847100.3 | D706: 1205234.2 | G706: 641866.1 | J706: 4778708.4 | K706: 945831.3 | L706: 2650142.1 | M706: 1530687.2 | N706: 415424.4 | O706: 1115262.8 | P706: 1119454.8 | U706: 693057.9 | V706: 299727.2 | W706: 393330.7 | Z706: 489677.2 | AD706: 328948.7 | AF706: 74367.9 | AG706: 875305.3 | AH706: 8268615.9 | AI706: 5249645.7 | AJ706: 1250308.2 | AL706: 1843400 | AM706: 51363.4 | AN706: 602103.2 | AO706: 7746512.2 | AP706: 522103.6 | AS706: =SUM(AI706:AK706) -> 6499953.9 | AT706: =AH706/AS706 -> 1.2721038
A707: 2005-04 | B707: 6660073 | C707: 1837731.2 | D707: 1190948.8 | G707: 646782.4 | J707: 4822341.8 | K707: 958561.2 | L707: 2681382.6 | M707: 1547953.3 | N707: 421121.2 | O707: 1126832.1 | P707: 1133429.4 | U707: 693525.3 | V707: 301125.6 | W707: 392399.7 | Z707: 488872.7 | AD707: 315321.9 | AF707: 75174 | AG707: 871442.8 | AH707: 8300756 | AI707: 5287721.8 | AJ707: 1285065.7 | AL707: 1847000.4 | AM707: 25657.7 | AN707: 604796.7 | AO707: 7765176.6 | AP707: 535579.4 | AS707: =SUM(AI707:AK707) -> 6572787.5 | AT707: =AH707/AS707 -> 1.2628974
A708: 2005-05 | B708: 6718434.7 | C708: 1869875.7 | D708: 1200847.5 | G708: 669028.2 | J708: 4848559 | K708: 968646.4 | L708: 2696086 | M708: 1545514.7 | N708: 427103.2 | O708: 1118411.5 | P708: 1150571.3 | U708: 691829.1 | V708: 298997.3 | W708: 392831.9 | Z708: 491997.5 | AD708: 322355.7 | AF708: 79336.9 | AG708: 874655.9 | AH708: 8380604.9 | AI708: 5313727.5 | AJ708: 1290175.2 | AL708: 1862675.7 | AM708: 56015.1 | AN708: 602508.1 | AO708: 7834926.4 | AP708: 545678.5 | AS708: =SUM(AI708:AK708) -> 6603902.7 | AT708: =AH708/AS708 -> 1.2690382
... A757: 2009-06 | B757: 9027353.8 | C757: 2244693.9 | D757: 1325037.2 | G757: 919656.7 | J757: 6782659.9 | K757: 1436281.5 | L757: 3860362.8 | M757: 2155005 | N757: 609653.5 | O757: 1545351.5 | P757: 1705357.9 | U757: 854687.7 | V757: 358029.4 | W757: 496658.3 | Z757: 631327.9 | AD757: 914890.7 | AF757: 77303.9 | AG757: 1520529.7 | AH757: 11947522 | AI757: 7516640.3 | AJ757: 1884587.9 | AL757: 2711146.1 | AM757: 104978.4 | AN757: 779802.5 | AO757: 11112567 | AP757: 834954.4 | AS757: =SUM(AI757:AK757) -> 9401228.2 | AT757: =AH757/AS757 -> 1.2708469
A758: 2009-07 | B758: 8967586 | C758: 2261358 | D758: 1343514.1 | E758: 975730.5 | F758: 367783.6 | G758: 917843.9 | H758: 216867.4 | I758: 700976.5 | J758: 6706228 | K758: 1395393 | L758: 3839164.7 | M758: 2142754 | N758: 607435.3 | O758: 1535318.7 | P758: 1696410.7 | U758: 850285.6 | V758: 356702.6 | W758: 493583 | Z758: 621384.7 | AC758: 186734.5 | AD758: 932190.7 | AF758: 85409 | AG758: 1498839.5 | AH758: 11772280 | AI758: 7498682.5 | AJ758: 1880462.7 | AK758: 5618219.9 | AL758: 2592417.4 | AM758: 92077.7 | AN758: 727193.1 | AO758: 10910371 | AP758: 861909.3 | AQ758: -47694.7 | AS758: =SUM(AI758:AK758) -> 14997365 | AT758: =AH758/AS758 -> 0.78495656
A759: 2009-08 | B759: 8921368.3 | C759: 2288206.9 | D759: 1380351.3 | E759: 977535.2 | F759: 402816.1 | G759: 907855.6 | H759: 217442.3 | I759: 690413.3 | J759: 6633161.4 | K759: 1363517.6 | L759: 3814526.2 | M759: 2125549.4 | N759: 605643.8 | O759: 1519905.6 | P759: 1688976.8 | U759: 849844.4 | V759: 355028.3 | W759: 494816.1 | Z759: 605273.2 | AC759: 189399.1 | AD759: 989741.9 | AF759: 89714.7 | AG759: 1461578.8 | AH759: 11708250 | AI759: 7536834.9 | AJ759: 1884511.6 | AK759: 5652323.3 | AL759: 2492953.7 | AM759: 138382.6 | AN759: 688300.5 | AO759: 10856472 | AP759: 851778.6 | AQ759: -38429.2 | AS759: =SUM(AI759:AK759) -> 15073670 | AT759: =AH759/AS759 -> 0.77673522
A760: 2009-09 | B760: 8842110.5 | C760: 2292341.8 | D760: 1395993.1 | E760: 982741.3 | F760: 413251.8 | G760: 896348.7 | H760: 218402.1 | I760: 677946.6 | J760: 6549768.6 | K760: 1337663.2 | L760: 3766206.2 | M760: 2086841.6 | N760: 603601.7 | O760: 1483239.9 | P760: 1679364.6 | U760: 847671.9 | V760: 351190.3 | W760: 496481.6 | Z760: 598227.3 | AC760: 192427.9 | AD760: 1060043.9 | AF760: 88345 | AG760: 1477549.9 | AH760: 11694180 | AI760: 7561225.3 | AJ760: 1864910.9 | AK760: 5696314.3 | AL760: 2403333.3 | AM760: 166216 | AN760: 685490.4 | AO760: 10816265 | AP760: 877915.3 | AQ760: -26327.8 | AS760: =SUM(AI760:AK760) -> 15122450 | AT760: =AH760/AS760 -> 0.7732993
A761: 2009-10 | B761: 8762429.7 | C761: 2283353.6 | D761: 1387795.4 | E761: 976763.3 | F761: 411032.1 | G761: 895558.2 | H761: 216675.7 | I761: 678882.5 | J761: 6479076.2 | K761: 1307863.2 | L761: 3741804.1 | M761: 2074311.7 | N761: 602444.7 | O761: 1471867 | P761: 1667492.5 | U761: 842646 | V761: 345983.5 | W761: 496662.5 | Z761: 586762.9 | AC761: 196584.5 | AD761: 1228920.3 | AF761: 80207.9 | AG761: 1482949.8 | AH761: 11752148 | AI761: 7603378.7 | AJ761: 1873294 | AK761: 5730084.7 | AL761: 2339999.6 | AM761: 202750.8 | AN761: 667968.6 | AO761: 10814098 | AP761: 938050.5 | AQ761: -13263.4 | AS761: =SUM(AI761:AK761) -> 15206757 | AT761: =AH761/AS761 -> 0.77282408
A762: 2009-11 | B762: 8819488.6 | C762: 2298314.9 | D762: 1413291.4 | E762: 989116.4 | F762: 424175.1 | G762: 885023.5 | H762: 214997.1 | I762: 670026.4 | J762: 6521173.7 | K762: 1290162.6 | L762: 3805558.4 | M762: 2146495.9 | N762: 605762.8 | O762: 1540733.1 | P762: 1659062.5 | U762: 841815 | V762: 344021.8 | W762: 497793.2 | Z762: 583637.7 | AC762: 200408.2 | AD762: 1248268.7 | AF762: 64227 | AG762: 1476901.4 | AH762: 11773994 | AI762: 7665998 | AJ762: 1878306 | AK762: 5787692.1 | AL762: 2302548.5 | AM762: 196235.9 | AN762: 666763.3 | AO762: 10831546 | AP762: 942448.4 | AQ762: -7634.1 | AS762: =SUM(AI762:AK762) -> 15331996 | AT762: =AH762/AS762 -> 0.76793615
A763: 2009-12 | B763: 8782690.1 | C763: 2325958.7 | D763: 1446157.8 | E763: 1001395.2 | F763: 444762.6 | G763: 879800.9 | H763: 214715.7 | I763: 665085.3 | J763: 6456731.3 | K763: 1265264.8 | L763: 3776798.6 | M763: 2135824.6 | N763: 603178.3 | O763: 1532646.4 | P763: 1640974 | U763: 835515.2 | V763: 335878.6 | W763: 499636.6 | Z763: 579152.7 | AC763: 200048.2 | AD763: 1241519.6 | AF763: 62439.8 | AG763: 1498250.2 | AH763: 11741762 | AI763: 7686464.8 | AJ763: 1889395.3 | AK763: 5797069.4 | AL763: 2257911.3 | AM763: 145224.5 | AN763: 663203.4 | AO763: 10752804 | AP763: 988958.1 | AQ763: -5687.9 | AS763: =SUM(AI763:AK763) -> 15372930 | AT763: =AH763/AS763 -> 0.7637947
A764: 2010-01 | B764: 8712227.4 | C764: 2324051.5 | D764: 1448660.7 | E764: 1000948.7 | F764: 447712 | G764: 875390.8 | H764: 212959.5 | I764: 662431.3 | J764: 6388175.9 | K764: 1238695.1 | L764: 3758474.5 | M764: 2128357.7 | N764: 599969.9 | O764: 1528387.9 | P764: 1630116.8 | U764: 819554.8 | V764: 323440.4 | W764: 496114.4 | Z764: 571451.4 | AC764: 199671.3 | AD764: 1257346 | AE764: 359258.2 | AF764: 58431.6 | AG764: 1499435 | AH764: 11687027 | AI764: 7674660.1 | AJ764: 1878443 | AK764: 5796217.2 | AL764: 1870780.1 | AM764: 124289.8 | AN764: 642529.4 | AO764: 10312259 | AP764: 1374767.5 | AQ764: -8817.3 | AS764: =SUM(AI764:AK764) -> 15349320 | AT764: =AH764/AS764 -> 0.76140355
A765: 2010-02 | B765: 8649214 | C765: 2327884.4 | D765: 1462902.4 | E765: 1009224.8 | F765: 453677.6 | G765: 864981.9 | H765: 208385.8 | I765: 656596.2 | J765: 6321329.6 | K765: 1223589.5 | L765: 3720975.7 | M765: 2099955.9 | N765: 599101 | O765: 1500854.9 | P765: 1621019.8 | U765: 812093.6 | V765: 317773 | W765: 494320.6 | Z765: 564670.8 | AC765: 199794.5 | AD765: 1313176.3 | AE765: 366179.7 | AF765: 60295 | AG765: 1512747.1 | AH765: 11701818 | AI765: 7698864.2 | AJ765: 1861328.9 | AK765: 5837535.3 | AL765: 1830870.4 | AM765: 165892.9 | AN765: 637283.3 | AO765: 10332911 | AP765: 1368906.7 | AQ765: -3190 | AS765: =SUM(AI765:AK765) -> 15397728 | AT765: =AH765/AS765 -> 0.75997038
A766: 2010-03 | B766: 8701046.3 | C766: 2317508.3 | D766: 1471430.5 | E766: 1000936.6 | F766: 470493.9 | G766: 846077.8 | H766: 203157.1 | I766: 642920.7 | J766: 6383537.9 | K766: 1210092.2 | L766: 3704364.3 | M766: 2094510 | N766: 599157.9 | O766: 1495352.1 | P766: 1609854.2 | U766: 886492.8 | V766: 391112.3 | W766: 495380.6 | Z766: 582588.6 | AC766: 206799.2 | AD766: 1244834.7 | AE766: 364117 | AF766: 49606.3 | AG766: 1502555.6 | AH766: 11655361 | AI766: 7690852.7 | AJ766: 1827919.9 | AK766: 5862932.7 | AL766: 1857816.2 | AM766: 120005.9 | AN766: 660313.9 | AO766: 10328989 | AP766: 1326372 | AQ766: -2073.3 | AS766: =SUM(AI766:AK766) -> 15381705 | AT766: =AH766/AS766 -> 0.75774178
A767: 2010-04 | B767: 9019780.1 | C767: 2315041.7 | D767: 1504017.8 | E767: 1006593.1 | F767: 497424.7 | G767: 811024 | H767: 190632.2 | I767: 620391.8 | J767: 6704738.4 | K767: 1207489.8 | L767: 3713999.8 | M767: 2113192.5 | N767: 601935 | O767: 1511257.5 | P767: 1600807.4 | U767: 1157957.2 | V767: 648239.2 | W767: 509718 | Z767: 625291.6 | AC767: 234887.6 | AD767: 1198259.3 | AE767: 349857.6 | AF767: 21773.1 | AG767: 1490141.4 | AH767: 11844924 | AI767: 7696805.4 | AJ767: 1781339.5 | AK767: 5915466 | AL767: 2107378 | AM767: 56355.5 | AN767: 662780.1 | AO767: 10523319 | AP767: 1321604.9 | AQ767: -2633.4 | AS767: =SUM(AI767:AK767) -> 15393611 | AT767: =AH767/AS767 -> 0.76947014
A768: 2010-05 | B768: 8968557.8 | C768: 2303089.3 | D768: 1504006.6 | E768: 1011440.9 | F768: 492565.7 | G768: 799082.7 | H768: 183508.9 | I768: 615573.8 | J768: 6665468.5 | K768: 1196715.9 | L768: 3699756.4 | M768: 2111773 | N768: 599486.2 | O768: 1512286.8 | P768: 1587983.4 | U768: 1149277.6 | V768: 640720.3 | W768: 508557.4 | Z768: 619718.5 | AC768: 233497.9 | AD768: 1182433.1 | AE768: 357272.3 | AF768: 17081.5 | AG768: 1505064.8 | AH768: 11796912 | AI768: 7677566.1 | AJ768: 1726189.5 | AK768: 5951376.6 | AL768: 2041791.7 | AM768: 48568.3 | AN768: 702647.6 | AO768: 10470574 | AP768: 1326337.9 | AQ768: 5894.8 | AS768: =SUM(AI768:AK768) -> 15355132 | AT768: =AH768/AS768 -> 0.76827158
A769: 2010-06 | B769: 8931888.4 | C769: 2294225.4 | D769: 1502075.9 | E769: 1007265.3 | F769: 494810.5 | G769: 792149.5 | H769: 178242.5 | I769: 613907 | J769: 6637663 | K769: 1190105.9 | L769: 3682359 | M769: 2106630.5 | N769: 597396.4 | O769: 1509234.2 | P769: 1575728.5 | U769: 1140086.3 | V769: 632257.7 | W769: 507828.7 | Z769: 625111.7 | AC769: 230994.4 | AD769: 1152507.9 | AE769: 350414.6 | AF769: 17139 | AG769: 1505158 | AH769: 11726113 | AI769: 7687576.3 | AJ769: 1716249.2 | AK769: 5971327.1 | AL769: 1989503.2 | AM769: 27437.6 | AN769: 705004 | AO769: 10409521 | AP769: 1316592.3 | AQ769: 9424.3 | AS769: =SUM(AI769:AK769) -> 15375153 | AT769: =AH769/AS769 -> 0.76266647
A770: 2010-07 | B770: 8965086.7 | C770: 2351982.9 | D770: 1559615.2 | E770: 1043640.2 | F770: 515975 | G770: 792367.7 | H770: 176698.5 | I770: 615669.2 | J770: 6613103.8 | K770: 1188974.2 | L770: 3661843.4 | M770: 2098563.5 | N770: 596335.6 | O770: 1502228 | P770: 1563279.8 | U770: 1136491 | V770: 626949.5 | W770: 509541.5 | Z770: 625795.2 | AC770: 226349.9 | AD770: 1183482.8 | AE770: 355332.8 | AF770: 18800.4 | AG770: 1492211.4 | AH770: 11788564 | AI770: 7728172.4 | AJ770: 1744399.5 | AK770: 5983772.9 | AL770: 1960491.8 | AM770: 65267.5 | AN770: 721226.2 | AO770: 10475158 | AP770: 1313406.2 | AQ770: 15214 | AS770: =SUM(AI770:AK770) -> 15456345 | AT770: =AH770/AS770 -> 0.76270064
A771: 2010-08 | B771: 8993581 | C771: 2388332.3 | D771: 1592686.1 | E771: 1056225.9 | F771: 536460.2 | G771: 795646.3 | H771: 173904.9 | I771: 621741.3 | J771: 6605248.7 | K771: 1187832.4 | L771: 3656050.7 | M771: 2101846.2 | N771: 594535.2 | O771: 1507311 | P771: 1554204.4 | U771: 1133580.2 | V771: 621672.3 | W771: 511907.8 | Z771: 627785.5 | AC771: 224083.9 | AD771: 1177907.5 | AE771: 359389.4 | AF771: 19083 | AG771: 1512184.5 | AH771: 11838061 | AI771: 7775414.7 | AJ771: 1760786 | AK771: 6014628.7 | AL771: 1966386.3 | AM771: 48900.5 | AN771: 743458.6 | AO771: 10534160 | AP771: 1303901.3 | AQ771: 19270.7 | AS771: =SUM(AI771:AK771) -> 15550829 | AT771: =AH771/AS771 -> 0.76124952
A772: 2010-09 | B772: 8988963.2 | C772: 2414020.1 | D772: 1616561.6 | E772: 1066531.7 | F772: 550029.8 | G772: 797458.5 | H772: 169006.5 | I772: 628452 | J772: 6574943.1 | K772: 1185927.2 | L772: 3642149.1 | M772: 2100587.8 | N772: 591642.1 | O772: 1508945.6 | P772: 1541561.3 | U772: 1121181.9 | V772: 616654.8 | W772: 504527.1 | Z772: 625684.9 | AC772: 222477.8 | AD772: 1138813.2 | AE772: 360339 | AF772: 21993.6 | AG772: 1501802.9 | AH772: 11789434 | AI772: 7797875.5 | AJ772: 1756295.4 | AK772: 6041580.1 | AL772: 1935581.2 | AM772: -2093 | AN772: 747231.7 | AO772: 10478595 | AP772: 1310838.8 | AQ772: 18976.2 | AS772: =SUM(AI772:AK772) -> 15595751 | AT772: =AH772/AS772 -> 0.75593885
A773: 2010-10 | B773: 9003022.1 | C773: 2439063.9 | D773: 1641131 | E773: 1091169.5 | F773: 549961.5 | G773: 797932.9 | H773: 167051.5 | I773: 630881.4 | J773: 6563958.2 | K773: 1184918.2 | L773: 3627162.6 | M773: 2099186.4 | N773: 588669.7 | O773: 1510516.7 | P773: 1527976.2 | U773: 1114659.1 | V773: 611965.4 | W773: 502693.6 | Z773: 637218.4 | AC773: 217411.1 | AD773: 1149558.6 | AE773: 368563.6 | AF773: 30196.5 | AG773: 1552032.8 | AH773: 11885962 | AI773: 7841647.9 | AJ773: 1762885.1 | AK773: 6078762.8 | AL773: 1928987.6 | AM773: -26741.2 | AN773: 801569.3 | AO773: 10545464 | AP773: 1340499 | AQ773: 20036.8 | AS773: =SUM(AI773:AK773) -> 15683296 | AT773: =AH773/AS773 -> 0.75787402
A774: 2010-11 | B774: 9017061.6 | C774: 2454510.4 | D774: 1657820.4 | E774: 1120394.3 | F774: 537426 | G774: 796690 | H774: 164500.3 | I774: 632189.7 | J774: 6562551.3 | K774: 1187119.6 | L774: 3623903.7 | M774: 2108899.3 | N774: 585385.4 | O774: 1523514 | P774: 1515004.3 | U774: 1109970.2 | V774: 608154.4 | W774: 501815.8 | Z774: 641557.7 | AC774: 214943.2 | AD774: 1105631.5 | AE774: 360687.4 | AF774: 29600.5 | AG774: 1531764.3 | AH774: 11829802 | AI774: 7883763.6 | AJ774: 1755022.8 | AK774: 6128740.8 | AL774: 1882279.8 | AM774: -41919.9 | AN774: 748609.1 | AO774: 10472733 | AP774: 1357069.5 | AQ774: 16835.8 | AS774: =SUM(AI774:AK774) -> 15767527 | AT774: =AH774/AS774 -> 0.75026362
A775: 2010-12 | B775: 8982732.1 | C775: 2426758.2 | D775: 1640856.4 | E775: 1110468.5 | F775: 530388 | G775: 785901.8 | H775: 159956.6 | I775: 625945.2 | J775: 6555973.9 | K775: 1192451.6 | L775: 3613638 | M775: 2113127.5 | N775: 581565.9 | O775: 1531561.6 | P775: 1500510.5 | U775: 1107190.3 | V775: 607386.9 | W775: 499803.4 | Z775: 642694.1 | AC775: 211059.7 | AD775: 1176220.3 | AE775: 345471.6 | AF775: 30553.7 | AG775: 1492163.5 | AH775: 11816082 | AI775: 7865811.9 | AJ775: 1724045.8 | AK775: 6141766.1 | AL775: 1886488.4 | AM775: -11318.9 | AN775: 717415.5 | AO775: 10458397 | AP775: 1357684.6 | AQ775: 5162.3 | AS775: =SUM(AI775:AK775) -> 15731624 | AT775: =AH775/AS775 -> 0.75110374
... A823: 2014-12 | B823: 10540060 | C823: 2932631.6 | D823: 2040376.5 | E823: 1400892.9 | F823: 639483.6 | G823: 892255 | H823: 129291 | I823: 762964.1 | J823: 7607428.1 | K823: 1773360.3 | L823: 3638639.9 | M823: 2033188.6 | N823: 458084.1 | O823: 1575104.5 | P823: 1605451.3 | U823: 1186716 | V823: 623451.6 | W823: 563264.4 | Z823: 1008712 | AC823: 109052.7 | AD823: 2865806 | AE823: 389444.2 | AF823: 10961.4 | AG823: 1367975.3 | AH823: 15065194 | AI823: 10469825 | AJ823: 1705280.7 | AK823: 8764544.4 | AL823: 1782817.8 | AM823: 499482.7 | AN823: 667391 | AO823: 13419517 | AP823: 1645677.3 | AQ823: 17812.2 | AS823: =SUM(AI823:AK823) -> 20939650 | AT823: =AH823/AS823 -> 0.71945776
A824: 2015-01 | B824: 10621735 | C824: 2959366.5 | D824: 2066807.1 | E824: 1417692.8 | F824: 649114.3 | G824: 892559.4 | H824: 129763.8 | I824: 762795.5 | J824: 7662368.6 | K824: 1791541.4 | L824: 3653686.1 | M824: 2038195.6 | N824: 457292.6 | O824: 1580903.1 | P824: 1615490.5 | Q824: 225060.6 | R824: 81679.1 | S824: 232157.6 | T824: 1076593.1 | U824: 1187227 | V824: 625665.4 | W824: 561561.6 | X824: 358304.8 | Y824: 203256.8 | Z824: 1029914.1 | AA824: 324121 | AB824: 705793.1 | AC824: 108530.6 | AD824: 2868935 | AE824: 414152.1 | AF824: 12795.6 | AG824: 1406205.3 | AH824: 15215292 | AI824: 10520654 | AJ824: 1703566.8 | AK824: 8817087.3 | AL824: 1798735.4 | AM824: 532767.8 | AN824: 718323.5 | AO824: 13570481 | AP824: 1644811.6 | AQ824: 25437.1 | AR824: 18762 | AS824: =SUM(AI824:AK824) -> 21041308 | AT824: =AH824/AS824 -> 0.72311533
A825: 2015-02 | B825: 10706716 | C825: 2990925.9 | D825: 2096822.2 | E825: 1440809.3 | F825: 656012.9 | G825: 894103.7 | H825: 128783.1 | I825: 765320.6 | J825: 7715790.2 | K825: 1808063.2 | L825: 3676094.2 | M825: 2045785.3 | N825: 456568.2 | O825: 1589217.1 | P825: 1630308.9 | Q825: 229095.7 | R825: 82259.9 | S825: 234833.7 | T825: 1084119.6 | U825: 1190670 | V825: 626879.1 | W825: 563790.8 | X825: 360199.5 | Y825: 203591.4 | Z825: 1040962.7 | AA825: 329204.8 | AB825: 711758 | AC825: 108018.5 | AD825: 2821530.2 | AE825: 415377 | AF825: 12083.5 | AG825: 1382587.3 | AH825: 15230276 | AI825: 10623789 | AJ825: 1712029.2 | AK825: 8911759.8 | AL825: 1772921.2 | AM825: 479583.4 | AN825: 688053.7 | AO825: 13564347 | AP825: 1665928.4 | AQ825: 20524.7 | AR825: 18616.6 | AS825: =SUM(AI825:AK825) -> 21247578 | AT825: =AH825/AS825 -> 0.71680055
A826: 2015-03 | B826: 10797639 | C826: 3004318.6 | D826: 2108969.1 | E826: 1460081.3 | F826: 648887.8 | G826: 895349.6 | H826: 129789.2 | I826: 765560.4 | J826: 7793320.7 | K826: 1834518.4 | L826: 3710441.5 | M826: 2056210.1 | N826: 455481.4 | O826: 1600728.7 | P826: 1654231.4 | Q826: 232684.4 | R826: 82723.1 | S826: 241038.6 | T826: 1097785.4 | U826: 1192900.5 | V826: 627253.3 | W826: 565647.2 | X826: 361701.1 | Y826: 203946.2 | Z826: 1055460.3 | AA826: 337885.3 | AB826: 717575 | AC826: 107521.8 | AD826: 2824706.7 | AE826: 415364.8 | AF826: 10846 | AG826: 1408344.2 | AH826: 15349379 | AI826: 10677880 | AJ826: 1708778.5 | AK826: 8969101.4 | AL826: 1817667.8 | AM826: 511292.7 | AN826: 696204.4 | AO826: 13703045 | AP826: 1646334.4 | AQ826: 22943.1 | AR826: 17088.4 | AS826: =SUM(AI826:AK826) -> 21355760 | AT826: =AH826/AS826 -> 0.71874657
A827: 2015-04 | B827: 10859365 | C827: 3020979.1 | D827: 2119831.3 | E827: 1464764.5 | F827: 655066.8 | G827: 901147.8 | H827: 129777.9 | I827: 771369.9 | J827: 7838385.8 | K827: 1847555.1 | L827: 3720085.4 | M827: 2058475.4 | N827: 453736.8 | O827: 1604738.6 | P827: 1661610 | Q827: 235927.4 | R827: 83267.1 | S827: 243851.4 | T827: 1098564.1 | U827: 1202066.4 | V827: 632028.7 | W827: 570037.7 | X827: 364295.4 | Y827: 205742.3 | Z827: 1068678.9 | AA827: 341921.7 | AB827: 726757.2 | AC827: 107104.8 | AD827: 2813996.3 | AE827: 427371.4 | AF827: 10969.2 | AG827: 1382138.7 | AH827: 15386736 | AI827: 10676967 | AJ827: 1689951.8 | AK827: 8987015 | AL827: 1831418.1 | AM827: 550190.7 | AN827: 670513.8 | AO827: 13729089 | AP827: 1657646.5 | AQ827: 26282.3 | AR827: 18394.4 | AS827: =SUM(AI827:AK827) -> 21353934 | AT827: =AH827/AS827 -> 0.72055745
A828: 2015-05 | B828: 10926287 | C828: 3047877.8 | D828: 2149370.8 | E828: 1480761.5 | F828: 668609.3 | G828: 898507 | H828: 129123.6 | I828: 769383.5 | J828: 7878409.4 | K828: 1863354.4 | L828: 3729732.6 | M828: 2057432.3 | N828: 451777.8 | O828: 1605654.5 | P828: 1672300.3 | Q828: 239248.1 | R828: 83927.7 | S828: 245848.3 | T828: 1103276.2 | U828: 1208463.2 | V828: 634533.8 | W828: 573929.4 | X828: 366891.5 | Y828: 207037.9 | Z828: 1076859.2 | AA828: 346450.1 | AB828: 730409.2 | AC828: 106620.7 | AD828: 2746424.8 | AE828: 414126.6 | AF828: 10831.4 | AG828: 1362415.2 | AH828: 15353464 | AI828: 10705881 | AJ828: 1688363.5 | AK828: 9017517.1 | AL828: 1834920 | AM828: 499569.9 | AN828: 646599.5 | AO828: 13686970 | AP828: 1666494.4 | AQ828: 17268 | AR828: 12745.8 | AS828: =SUM(AI828:AK828) -> 21411761 | AT828: =AH828/AS828 -> 0.71705753
A829: 2015-06 | B829: 10982470 | C829: 3053256.7 | D829: 2155982.3 | E829: 1490924.4 | F829: 665057.9 | G829: 897274.4 | H829: 127036.6 | I829: 770237.8 | J829: 7929213.3 | K829: 1880116.5 | L829: 3748425.1 | M829: 2061997.8 | N829: 449236.6 | O829: 1612761.2 | P829: 1686427.3 | Q829: 242652.5 | R829: 84665.9 | S829: 248049.7 | T829: 1111059.2 | U829: 1214146.2 | V829: 637281.3 | W829: 576865 | X829: 369032.7 | Y829: 207832.3 | Z829: 1086525.4 | AA829: 351962.7 | AB829: 734562.7 | AC829: 106304.2 | AD829: 2685473.1 | AE829: 407229 | AF829: 11491.3 | AG829: 1355109.6 | AH829: 15335469 | AI829: 10750630 | AJ829: 1691697.3 | AK829: 9058933 | AL829: 1837386.5 | AM829: 443223.6 | AN829: 640334.3 | AO829: 13671575 | AP829: 1663894.1 | AQ829: 9962 | AR829: 7023.9 | AS829: =SUM(AI829:AK829) -> 21501261 | AT829: =AH829/AS829 -> 0.7132358
A830: 2015-07 | B830: 11009963 | C830: 3043025.5 | D830: 2151309.9 | E830: 1494047 | F830: 657262.9 | G830: 891715.6 | H830: 125881 | I830: 765834.6 | J830: 7966937.1 | K830: 1889448.9 | L830: 3762400.3 | M830: 2059853.3 | N830: 446945.9 | O830: 1612907.4 | P830: 1702547 | Q830: 246038.8 | R830: 85133.4 | S830: 252282.8 | T830: 1119092.1 | U830: 1221354.2 | V830: 641110.6 | W830: 580243.6 | X830: 371119.5 | Y830: 209124.1 | Z830: 1093733.8 | AA830: 352489 | AB830: 741244.8 | AC830: 106229.4 | AD830: 2687648.1 | AE830: 420340.3 | AF830: 9976.5 | AG830: 1350385.5 | AH830: 15372084 | AI830: 10783735 | AJ830: 1698323.5 | AK830: 9085411.7 | AL830: 1836607.3 | AM830: 446301 | AN830: 628398.5 | AO830: 13695042 | AP830: 1677041.7 | AQ830: 12274.8 | AR830: 7459.7 | AS830: =SUM(AI830:AK830) -> 21567470 | AT830: =AH830/AS830 -> 0.71274393
A831: 2015-08 | B831: 11076358 | C831: 3057455.5 | D831: 2165647.1 | E831: 1514040.3 | F831: 651606.8 | G831: 891808.3 | H831: 125304.6 | I831: 766503.7 | J831: 8018902.4 | K831: 1903533.4 | L831: 3778175.2 | M831: 2060469.5 | N831: 444184.3 | O831: 1616285.2 | P831: 1717705.7 | Q831: 249256.5 | R831: 85387.2 | S831: 256709.3 | T831: 1126352.7 | U831: 1228522 | V831: 645291.4 | W831: 583230.6 | X831: 372936.4 | Y831: 210294.2 | Z831: 1108671.8 | AA831: 360056.8 | AB831: 748614.9 | AC831: 107040.9 | AD831: 2685577.3 | AE831: 401668.4 | AF831: 9338 | AG831: 1361359.2 | AH831: 15427260 | AI831: 10838072 | AJ831: 1709590 | AK831: 9128482.3 | AL831: 1834244.3 | AM831: 443289.6 | AN831: 632938.7 | AO831: 13748545 | AP831: 1678714.9 | AQ831: 13550.3 | AR831: 9486.6 | AS831: =SUM(AI831:AK831) -> 21676145 | AT831: =AH831/AS831 -> 0.71171604
A832: 2015-09 | B832: 11116585 | C832: 3049057.3 | D832: 2163378.6 | E832: 1521631.6 | F832: 641747 | G832: 885678.7 | H832: 124137.6 | I832: 761541.1 | J832: 8067528 | K832: 1915131.9 | L832: 3795293.1 | M832: 2061263.7 | N832: 444063.6 | O832: 1617200.1 | P832: 1734029.4 | Q832: 252118.1 | R832: 85813 | S832: 260602.2 | T832: 1135496.1 | U832: 1236595.9 | V832: 649362.5 | W832: 587233.3 | X832: 375704 | Y832: 211529.4 | Z832: 1120507.1 | AA832: 366968 | AB832: 753539.1 | AC832: 106448.2 | AD832: 2637639.6 | AE832: 393905.6 | AF832: 10536.8 | AG832: 1357904.2 | AH832: 15410123 | AI832: 10863965 | AJ832: 1697186.2 | AK832: 9166779.2 | AL832: 1807914.9 | AM832: 437928.3 | AN832: 615941 | AO832: 13725750 | AP832: 1684373.7 | AQ832: 13237.8 | AR832: 9775.6 | AS832: =SUM(AI832:AK832) -> 21727931 | AT832: =AH832/AS832 -> 0.70923106
...

Sheet results
A1: Time | C1: Credit Card | D1: Other Asset | E1: Total Asset | F1: Total Liability | G1: Total Deposits | H1: Residual (NW) | I1: Residual (NW) - D | J1: CC / TA | K1: OA / CC | L1: TA / CC | M1: TL / CC | N1: TA / TL | O1: TA / NW
A2: ='raw data'!A650 -> 2000-07 | B2: ='raw data'!U650 -> 531142 | C2: ='raw data'!V650 -> 211897.8 | D2: =E2-C2 -> 5693184 | E2: ='raw data'!AH650 -> 5905081.8 | F2: ='raw data'!AO650 -> 5678886 | G2: ='raw data'!AS650 -> 4521704.5 | H2: =E2-F2 -> 226195.8 | I2: =E2-G2 -> 1383377.3 | J2: =C2/E2*100 -> 3.5883974 | K2: =D2/C2 -> 26.867594 | L2: =E2/C2 -> 27.867594 | M2: =F2/C2 -> 26.800118 | N2: =E2/F2 -> 1.039831 | O2: =E2/H2 -> 26.106063 | P2: =E2/I2 -> 4.2685982
A3: ='raw data'!A651 -> 2000-08 | B3: ='raw data'!U651 -> 538855.4 | C3: ='raw data'!V651 -> 217854 | D3: =E3-C3 -> 5716299.2 | E3: ='raw data'!AH651 -> 5934153.2 | F3: ='raw data'!AO651 -> 5714051.1 | G3: ='raw data'!AS651 -> 4564306.7 | H3: =E3-F3 -> 220102.1 | I3: =E3-G3 -> 1369846.5 | J3: =C3/E3*100 -> 3.6711893 | K3: =D3/C3 -> 26.239129 | L3: =E3/C3 -> 27.239129 | M3: =F3/C3 -> 26.22881 | N3: =E3/F3 -> 1.0385194 | O3: =E3/H3 -> 26.960911 | P3: =E3/I3 -> 4.3319841
A4: ='raw data'!A652 -> 2000-09 | B4: ='raw data'!U652 -> 543717.1 | C4: ='raw data'!V652 -> 222410.9 | D4: =E4-C4 -> 5751305.6 | E4: ='raw data'!AH652 -> 5973716.5 | F4: ='raw data'!AO652 -> 5736376.6 | G4: ='raw data'!AS652 -> 4578304.4 | H4: =E4-F4 -> 237339.9 | I4: =E4-G4 -> 1395412.1 | J4: =C4/E4*100 -> 3.7231579 | K4: =D4/C4 -> 25.85892 | L4: =E4/C4 -> 26.85892 | M4: =F4/C4 -> 25.791796 | N4: =E4/F4 -> 1.0413745 | O4: =E4/H4 -> 25.169457 | P4: =E4/I4 -> 4.2809694
A5: ='raw data'!A653 -> 2000-10 | B5: ='raw data'!U653 -> 544271.9 | C5: ='raw data'!V653 -> 220752.4 | D5: =E5-C5 -> 5770217.5 | E5: ='raw data'!AH653 -> 5990969.9 | F5: ='raw data'!AO653 -> 5730192.1 | G5: ='raw data'!AS653 -> 4585167.3 | H5: =E5-F5 -> 260777.8 | I5: =E5-G5 -> 1405802.6 | J5: =C5/E5*100 -> 3.6847523 | K5: =D5/C5 -> 26.138866 | L5: =E5/C5 -> 27.138866 | M5: =F5/C5 -> 25.957553 | N5: =E5/F5 -> 1.0455094 | O5: =E5/H5 -> 22.973466 | P5: =E5/I5 -> 4.2616011
A6: ='raw data'!A654 -> 2000-11 | B6: ='raw data'!U654 -> 548263.8 | C6: ='raw data'!V654 -> 222338.7 | D6: =E6-C6 -> 5768300.6 | E6: ='raw data'!AH654 -> 5990639.3 | F6: ='raw data'!AO654 -> 5716039.2 | G6: ='raw data'!AS654 -> 4576630.5 | H6: =E6-F6 -> 274600.1 | I6: =E6-G6 -> 1414008.8 | J6: =C6/E6*100 -> 3.7114353 | K6: =D6/C6 -> 25.943754 | L6: =E6/C6 -> 26.943754 | M6: =F6/C6 -> 25.708701 | N6: =E6/F6 -> 1.0480403 | O6: =E6/H6 -> 21.815867 | P6: =E6/I6 -> 4.2366351
A7: ='raw data'!A655 -> 2000-12 | B7: ='raw data'!U655 -> 555531.4 | C7: ='raw data'!V655 -> 228197.3 | D7: =E7-C7 -> 5839338.5 | E7: ='raw data'!AH655 -> 6067535.8 | F7: ='raw data'!AO655 -> 5809431.8 | G7: ='raw data'!AS655 -> 4646582.5 | H7: =E7-F7 -> 258104 | I7: =E7-G7 -> 1420953.3 | J7: =C7/E7*100 -> 3.7609551 | K7: =D7/C7 -> 25.58899 | L7: =E7/C7 -> 26.58899 | M7: =F7/C7 -> 25.457934 | N7: =E7/F7 -> 1.0444284 | O7: =E7/H7 -> 23.508104 | P7: =E7/I7 -> 4.2700459
A8: ='raw data'!A656 -> 2001-01 | B8: ='raw data'!U656 -> 558590.1 | C8: ='raw data'!V656 -> 230967.4 | D8: =E8-C8 -> 5920051.7 | E8: ='raw data'!AH656 -> 6151019.1 | F8: ='raw data'!AO656 -> 5877247 | G8: ='raw data'!AS656 -> 4688421.9 | H8: =E8-F8 -> 273772.1 | I8: =E8-G8 -> 1462597.2 | J8: =C8/E8*100 -> 3.7549453 | K8: =D8/C8 -> 25.631547 | L8: =E8/C8 -> 26.631547 | M8: =F8/C8 -> 25.446219 | N8: =E8/F8 -> 1.0465817 | O8: =E8/H8 -> 22.467662 | P8: =E8/I8 -> 4.2055455
A9: ='raw data'!A657 -> 2001-02 | B9: ='raw data'!U657 -> 557858 | C9: ='raw data'!V657 -> 229551.1 | D9: =E9-C9 -> 5908417.3 | E9: ='raw data'!AH657 -> 6137968.4 | F9: ='raw data'!AO657 -> 5870782.7 | G9: ='raw data'!AS657 -> 4700436.3 | H9: =E9-F9 -> 267185.7 | I9: =E9-G9 -> 1437532.1 | J9: =C9/E9*100 -> 3.7398547 | K9: =D9/C9 -> 25.739007 | L9: =E9/C9 -> 26.739007 | M9: =F9/C9 -> 25.575058 | N9: =E9/F9 -> 1.0455111 | O9: =E9/H9 -> 22.972668 | P9: =E9/I9 -> 4.2697957
A10: ='raw data'!A658 -> 2001-03 | B10: ='raw data'!U658 -> 557205.5 | C10: ='raw data'!V658 -> 228144.8 | D10: =E10-C10 -> 5960646.7 | E10: ='raw data'!AH658 -> 6188791.5 | F10: ='raw data'!AO658 -> 5919212.6 | G10: ='raw data'!AS658 -> 4737073.4 | H10: =E10-F10 -> 269578.9 | I10: =E10-G10 -> 1451718.1 | J10: =C10/E10*100 -> 3.6864192 | K10: =D10/C10 -> 26.126595 | L10: =E10/C10 -> 27.126595 | M10: =F10/C10 -> 25.944981 | N10: =E10/F10 -> 1.045543 | O10: =E10/H10 -> 22.957255 | P10: =E10/I10 -> 4.2630808
A11: ='raw data'!A659 -> 2001-04 | B11: ='raw data'!U659 -> 561350.2 | C11: ='raw data'!V659 -> 232200.8 | D11: =E11-C11 -> 5996841.9 | E11: ='raw data'!AH659 -> 6229042.7 | F11: ='raw data'!AO659 -> 5948783.7 | G11: ='raw data'!AS659 -> 4783168.3 | H11: =E11-F11 -> 280259 | I11: =E11-G11 -> 1445874.4 | J11: =C11/E11*100 -> 3.7277124 | K11: =D11/C11 -> 25.826104 | L11: =E11/C11 -> 26.826104 | M11: =F11/C11 -> 25.619135 | N11: =E11/F11 -> 1.047112 | O11: =E11/H11 -> 22.226022 | P11: =E11/I11 -> 4.3081492
A12: ='raw data'!A660 -> 2001-05 | B12: ='raw data'!U660 -> 566114.6 | C12: ='raw data'!V660 -> 235574.1 | D12: =E12-C12 -> 5983711.3 | E12: ='raw data'!AH660 -> 6219285.4 | F12: ='raw data'!AO660 -> 5946266.5 | G12: ='raw data'!AS660 -> 4814665.4 | H12: =E12-F12 -> 273018.9 | I12: =E12-G12 -> 1404620 | J12: =C12/E12*100 -> 3.7878001 | K12: =D12/C12 -> 25.400548 | L12: =E12/C12 -> 26.400548 | M12: =F12/C12 -> 25.241597 | N12: =E12/F12 -> 1.0459143 | O12: =E12/H12 -> 22.779688 | P12: =E12/I12 -> 4.4277352
A13: ='raw data'!A661 -> 2001-06 | B13: ='raw data'!U661 -> 564557.4 | C13: ='raw data'!V661 -> 233267.1 | D13: =E13-C13 -> 5974287.5 | E13: ='raw data'!AH661 -> 6207554.6 | F13: ='raw data'!AO661 -> 5932611.4 | G13: ='raw data'!AS661 -> 4833647.1 | H13: =E13-F13 -> 274943.2 | I13: =E13-G13 -> 1373907.5 | J13: =C13/E13*100 -> 3.7577938 | K13: =D13/C13 -> 25.611359 | L13: =E13/C13 -> 26.611359 | M13: =F13/C13 -> 25.432697 | N13: =E13/F13 -> 1.0463444 | O13: =E13/H13 -> 22.577589 | P13: =E13/I13 -> 4.5181751
... A43: ='raw data'!A691 -> 2003-12 | B43: ='raw data'!U691 -> 664772.1 | C43: ='raw data'!V691 -> 280989.7 | D43: =E43-C43 -> 7033550.5 | E43: ='raw data'!AH691 -> 7314540.2 | F43: ='raw data'!AO691 -> 6930551.9 | G43: ='raw data'!AS691 -> 5631953.6 | H43: =E43-F43 -> 383988.3 | I43: =E43-G43 -> 1682586.6 | J43: =C43/E43*100 -> 3.8415224 | K43: =D43/C43 -> 25.031346 | L43: =E43/C43 -> 26.031346 | M43: =F43/C43 -> 24.66479 | N43: =E43/F43 -> 1.0554052 | O43: =E43/H43 -> 19.048862 | P43: =E43/I43 -> 4.3471998
A44: ='raw data'!A692 -> 2004-01 | B44: ='raw data'!U692 -> 671934.4 | C44: ='raw data'!V692 -> 283276.6 | D44: =E44-C44 -> 7118876.4 | E44: ='raw data'!AH692 -> 7402153 | F44: ='raw data'!AO692 -> 7023084 | G44: ='raw data'!AS692 -> 5684357.4 | H44: =E44-F44 -> 379069 | I44: =E44-G44 -> 1717795.6 | J44: =C44/E44*100 -> 3.8269487 | K44: =D44/C44 -> 25.130478 | L44: =E44/C44 -> 26.130478 | M44: =F44/C44 -> 24.79232 | N44: =E44/F44 -> 1.0539747 | O44: =E44/H44 -> 19.527192 | P44: =E44/I44 -> 4.3091 | Q44: Avg CC/TA
A45: ='raw data'!A693 -> 2004-02 | B45: ='raw data'!U693 -> 671297.8 | C45: ='raw data'!V693 -> 281560.2 | D45: =E45-C45 -> 7239054.6 | E45: ='raw data'!AH693 -> 7520614.8 | F45: ='raw data'!AO693 -> 7130441.1 | G45: ='raw data'!AS693 -> 5749278.9 | H45: =E45-F45 -> 390173.7 | I45: =E45-G45 -> 1771335.9 | J45: =C45/E45*100 -> 3.7438455 | K45: =D45/C45 -> 25.710504 | L45: =E45/C45 -> 26.710504 | M45: =F45/C45 -> 25.324748 | N45: =E45/F45 -> 1.0547194 | O45: =E45/H45 -> 19.275043 | P45: =E45/I45 -> 4.2457305 | Q45: =AVERAGE(J44:J55) -> 3.6979737
A46: ='raw data'!A694 -> 2004-03 | B46: ='raw data'!U694 -> 669655.6 | C46: ='raw data'!V694 -> 279474.5 | D46: =E46-C46 -> 7272080.8 | E46: ='raw data'!AH694 -> 7551555.3 | F46: ='raw data'!AO694 -> 7160907.1 | G46: ='raw data'!AS694 -> 5828558.8 | H46: =E46-F46 -> 390648.2 | I46: =E46-G46 -> 1722996.5 | J46: =C46/E46*100 -> 3.7008866 | K46: =D46/C46 -> 26.020552 | L46: =E46/C46 -> 27.020552 | M46: =F46/C46 -> 25.622757 | N46: =E46/F46 -> 1.0545529 | O46: =E46/H46 -> 19.330833 | P46: =E46/I46 -> 4.3828036 | Q46: Avg TA/NW
A47: ='raw data'!A695 -> 2004-04 | B47: ='raw data'!U695 -> 672082.9 | C47: ='raw data'!V695 -> 281049.1 | D47: =E47-C47 -> 7357249.4 | E47: ='raw data'!AH695 -> 7638298.5 | F47: ='raw data'!AO695 -> 7202602.1 | G47: ='raw data'!AS695 -> 5891009 | H47: =E47-F47 -> 435696.4 | I47: =E47-G47 -> 1747289.5 | J47: =C47/E47*100 -> 3.6794726 | K47: =D47/C47 -> 26.177808 | L47: =E47/C47 -> 27.177808 | M47: =F47/C47 -> 25.627558 | N47: =E47/F47 -> 1.0604915 | O47: =E47/H47 -> 17.531241 | P47: =E47/I47 -> 4.3715128 | Q47: =AVERAGE(O44:O55) -> 18.060952
A48: ='raw data'!A696 -> 2004-05 | B48: ='raw data'!U696 -> 677176.8 | C48: ='raw data'!V696 -> 284903.9 | D48: =E48-C48 -> 7379888.4 | E48: ='raw data'!AH696 -> 7664792.3 | F48: ='raw data'!AO696 -> 7233687.2 | G48: ='raw data'!AS696 -> 6000669.7 | H48: =E48-F48 -> 431105.1 | I48: =E48-G48 -> 1664122.6 | J48: =C48/E48*100 -> 3.7170466 | K48: =D48/C48 -> 25.90308 | L48: =E48/C48 -> 26.90308 | M48: =F48/C48 -> 25.38992 | N48: =E48/F48 -> 1.0595969 | O48: =E48/H48 -> 17.779405 | P48: =E48/I48 -> 4.605906 | Q48: Avg OA/CC
A49: ='raw data'!A697 -> 2004-06 | B49: ='raw data'!U697 -> 679977.5 | C49: ='raw data'!V697 -> 287433.6 | D49: =E49-C49 -> 7454905.4 | E49: ='raw data'!AH697 -> 7742339 | F49: ='raw data'!AO697 -> 7331544.1 | G49: ='raw data'!AS697 -> 6060581.5 | H49: =E49-F49 -> 410794.9 | I49: =E49-G49 -> 1681757.5 | J49: =C49/E49*100 -> 3.7124905 | K49: =D49/C49 -> 25.936096 | L49: =E49/C49 -> 26.936096 | M49: =F49/C49 -> 25.506914 | N49: =E49/F49 -> 1.0560312 | O49: =E49/H49 -> 18.847213 | P49: =E49/I49 -> 4.603719 | Q49: =AVERAGE(K44:K55) -> 26.047342
A50: ='raw data'!A698 -> 2004-07 | B50: ='raw data'!U698 -> 680087 | C50: ='raw data'!V698 -> 287878.6 | D50: =E50-C50 -> 7557867.1 | E50: ='raw data'!AH698 -> 7845745.7 | F50: ='raw data'!AO698 -> 7433368.8 | G50: ='raw data'!AS698 -> 6156965.3 | H50: =E50-F50 -> 412376.9 | I50: =E50-G50 -> 1688780.4 | J50: =C50/E50*100 -> 3.6692318 | K50: =D50/C50 -> 26.253661 | L50: =E50/C50 -> 27.253661 | M50: =F50/C50 -> 25.821193 | N50: =E50/F50 -> 1.0554764 | O50: =E50/H50 -> 19.025667 | P50: =E50/I50 -> 4.6458058 | Q50: Avg TA/TL
A51: ='raw data'!A699 -> 2004-08 | B51: ='raw data'!U699 -> 683613.5 | C51: ='raw data'!V699 -> 290661.3 | D51: =E51-C51 -> 7586471.1 | E51: ='raw data'!AH699 -> 7877132.4 | F51: ='raw data'!AO699 -> 7445370.8 | G51: ='raw data'!AS699 -> 6169053.8 | H51: =E51-F51 -> 431761.6 | I51: =E51-G51 -> 1708078.6 | J51: =C51/E51*100 -> 3.689938 | K51: =D51/C51 -> 26.100727 | L51: =E51/C51 -> 27.100727 | M51: =F51/C51 -> 25.615281 | N51: =E51/F51 -> 1.0579906 | O51: =E51/H51 -> 18.244171 | P51: =E51/I51 -> 4.611692 | Q51: =AVERAGE(N44:N55) -> 1.0588514
A52: ='raw data'!A700 -> 2004-09 | B52: ='raw data'!U700 -> 686419.5 | C52: ='raw data'!V700 -> 294299.2 | D52: =E52-C52 -> 7666584.1 | E52: ='raw data'!AH700 -> 7960883.3 | F52: ='raw data'!AO700 -> 7498189.3 | G52: ='raw data'!AS700 -> 6202452.8 | H52: =E52-F52 -> 462694 | I52: =E52-G52 -> 1758430.5 | J52: =C52/E52*100 -> 3.6968159 | K52: =D52/C52 -> 26.050306 | L52: =E52/C52 -> 27.050306 | M52: =F52/C52 -> 25.478116 | N52: =E52/F52 -> 1.0617074 | O52: =E52/H52 -> 17.205504 | P52: =E52/I52 -> 4.5272664 | Q52: Avg TL/CC
A53: ='raw data'!A701 -> 2004-10 | B53: ='raw data'!U701 -> 684346.8 | C53: ='raw data'!V701 -> 291309 | D53: =E53-C53 -> 7682430.6 | E53: ='raw data'!AH701 -> 7973739.6 | F53: ='raw data'!AO701 -> 7493249 | G53: ='raw data'!AS701 -> 6241305.6 | H53: =E53-F53 -> 480490.6 | I53: =E53-G53 -> 1732434 | J53: =C53/E53*100 -> 3.6533548 | K53: =D53/C53 -> 26.372102 | L53: =E53/C53 -> 27.372102 | M53: =F53/C53 -> 25.722683 | N53: =E53/F53 -> 1.0641231 | O53: =E53/H53 -> 16.594996 | P53: =E53/I53 -> 4.6026224 | Q53: =AVERAGE(M44:M55) -> 25.543579
A54: ='raw data'!A702 -> 2004-11 | B54: ='raw data'!U702 -> 680706.3 | C54: ='raw data'!V702 -> 287768.8 | D54: =E54-C54 -> 7721897.7 | E54: ='raw data'!AH702 -> 8009666.5 | F54: ='raw data'!AO702 -> 7537779.5 | G54: ='raw data'!AS702 -> 6313141.4 | H54: =E54-F54 -> 471887 | I54: =E54-G54 -> 1696525.1 | J54: =C54/E54*100 -> 3.5927688 | K54: =D54/C54 -> 26.833686 | L54: =E54/C54 -> 27.833686 | M54: =F54/C54 -> 26.193873 | N54: =E54/F54 -> 1.0626029 | O54: =E54/H54 -> 16.973696 | P54: =E54/I54 -> 4.721219
A55: ='raw data'!A703 -> 2004-12 | B55: ='raw data'!U703 -> 691415 | C55: ='raw data'!V703 -> 296868.7 | D55: =E55-C55 -> 7742069.1 | E55: ='raw data'!AH703 -> 8038937.8 | F55: ='raw data'!AO703 -> 7548653.1 | G55: ='raw data'!AS703 -> 6358149.7 | H55: =E55-F55 -> 490284.7 | I55: =E55-G55 -> 1680788.1 | J55: =C55/E55*100 -> 3.6928846 | K55: =D55/C55 -> 26.079102 | L55: =E55/C55 -> 27.079102 | M55: =F55/C55 -> 25.427582 | N55: =E55/F55 -> 1.06495 | O55: =E55/H55 -> 16.396469 | P55: =E55/I55 -> 4.7828384
A56: ='raw data'!A704 -> 2005-01 | B56: ='raw data'!U704 -> 693794.9 | C56: ='raw data'!V704 -> 303790.4 | D56: =E56-C56 -> 7792052.7 | E56: ='raw data'!AH704 -> 8095843.1 | F56: ='raw data'!AO704 -> 7607596.5 | G56: ='raw data'!AS704 -> 6424894.4 | H56: =E56-F56 -> 488246.6 | I56: =E56-G56 -> 1670948.7 | J56: =C56/E56*100 -> 3.7524245 | K56: =D56/C56 -> 25.649437 | L56: =E56/C56 -> 26.649437 | M56: =F56/C56 -> 25.042254 | N56: =E56/F56 -> 1.0641788 | O56: =E56/H56 -> 16.581463 | P56: =E56/I56 -> 4.8450578
A57: ='raw data'!A705 -> 2005-02 | B57: ='raw data'!U705 -> 690746.4 | C57: ='raw data'!V705 -> 299128.9 | D57: =E57-C57 -> 7874900.6 | E57: ='raw data'!AH705 -> 8174029.5 | F57: ='raw data'!AO705 -> 7661914 | G57: ='raw data'!AS705 -> 6462188.8 | H57: =E57-F57 -> 512115.5 | I57: =E57-G57 -> 1711840.7 | J57: =C57/E57*100 -> 3.6595036 | K57: =D57/C57 -> 26.326111 | L57: =E57/C57 -> 27.326111 | M57: =F57/C57 -> 25.614088 | N57: =E57/F57 -> 1.0668391 | O57: =E57/H57 -> 15.961301 | P57: =E57/I57 -> 4.7749943
A58: ='raw data'!A706 -> 2005-03 | B58: ='raw data'!U706 -> 693057.9 | C58: ='raw data'!V706 -> 299727.2 | D58: =E58-C58 -> 7968888.7 | E58: ='raw data'!AH706 -> 8268615.9 | F58: ='raw data'!AO706 -> 7746512.2 | G58: ='raw data'!AS706 -> 6499953.9 | H58: =E58-F58 -> 522103.7 | I58: =E58-G58 -> 1768662 | J58: =C58/E58*100 -> 3.6248775 | K58: =D58/C58 -> 26.587139 | L58: =E58/C58 -> 27.587139 | M58: =F58/C58 -> 25.845209 | N58: =E58/F58 -> 1.0673986 | O58: =E58/H58 -> 15.837114 | P58: =E58/I58 -> 4.6750684
A59: ='raw data'!A707 -> 2005-04 | B59: ='raw data'!U707 -> 693525.3 | C59: ='raw data'!V707 -> 301125.6 | D59: =E59-C59 -> 7999630.4 | E59: ='raw data'!AH707 -> 8300756 | F59: ='raw data'!AO707 -> 7765176.6 | G59: ='raw data'!AS707 -> 6572787.5 | H59: =E59-F59 -> 535579.4 | I59: =E59-G59 -> 1727968.5 | J59: =C59/E59*100 -> 3.6276889 | K59: =D59/C59 -> 26.56576 | L59: =E59/C59 -> 27.56576 | M59: =F59/C59 -> 25.787169 | N59: =E59/F59 -> 1.068972 | O59: =E59/H59 -> 15.498647 | P59: =E59/I59 -> 4.8037658
A60: ='raw data'!A708 -> 2005-05 | B60: ='raw data'!U708 -> 691829.1 | C60: ='raw data'!V708 -> 298997.3 | D60: =E60-C60 -> 8081607.6 | E60: ='raw data'!AH708 -> 8380604.9 | F60: ='raw data'!AO708 -> 7834926.4 | G60: ='raw data'!AS708 -> 6603902.7 | H60: =E60-F60 -> 545678.5 | I60: =E60-G60 -> 1776702.2 | J60: =C60/E60*100 -> 3.5677293 | K60: =D60/C60 -> 27.029032 | L60: =E60/C60 -> 28.029032 | M60: =F60/C60 -> 26.204004 | N60: =E60/F60 -> 1.0696469 | O60: =E60/H60 -> 15.358137 | P60: =E60/I60 -> 4.7169441
A61: ='raw data'!A709 -> 2005-06 | B61: ='raw data'!U709 -> 692900.4 | C61: ='raw data'!V709 -> 301594.9 | D61: =E61-C61 -> 8126343.4 | E61: ='raw data'!AH709 -> 8427938.3 | F61: ='raw data'!AO709 -> 7877526.3 | G61: ='raw data'!AS709 -> 6690853.8 | H61: =E61-F61 -> 550412 | I61: =E61-G61 -> 1737084.5 | J61: =C61/E61*100 -> 3.5785134 | K61: =D61/C61 -> 26.944565 | L61: =E61/C61 -> 27.944565 | M61: =F61/C61 -> 26.119561 | N61: =E61/F61 -> 1.0698712 | O61: =E61/H61 -> 15.312054 | P61: =E61/I61 -> 4.8517722
A62: ='raw data'!A710 -> 2005-07 | B62: ='raw data'!U710 -> 697638.4 | C62: ='raw data'!V710 -> 302440.1 | D62: =E62-C62 -> 8171457.1 | E62: ='raw data'!AH710 -> 8473897.2 | F62: ='raw data'!AO710 -> 7939848.9 | G62: ='raw data'!AS710 -> 6730293.7 | H62: =E62-F62 -> 534048.3 | I62: =E62-G62 -> 1743603.5 | J62: =C62/E62*100 -> 3.5690792 | K62: =D62/C62 -> 27.018431 | L62: =E62/C62 -> 28.018431 | M62: =F62/C62 -> 26.252633 | N62: =E62/F62 -> 1.0672618 | O62: =E62/H62 -> 15.867286 | P62: =E62/I62 -> 4.8599909
A63: ='raw data'!A711 -> 2005-08 | B63: ='raw data'!U711 -> 705855.3 | C63: ='raw data'!V711 -> 302007.9 | D63: =E63-C63 -> 8269716.8 | E63: ='raw data'!AH711 -> 8571724.7 | F63: ='raw data'!AO711 -> 8032491.9 | G63: ='raw data'!AS711 -> 6832019.6 | H63: =E63-F63 -> 539232.8 | I63: =E63-G63 -> 1739705.1 | J63: =C63/E63*100 -> 3.5233038 | K63: =D63/C63 -> 27.382452 | L63: =E63/C63 -> 28.382452 | M63: =F63/C63 -> 26.59696 | N63: =E63/F63 -> 1.0671314 | O63: =E63/H63 -> 15.896149 | P63: =E63/I63 -> 4.9271136
A64: ='raw data'!A712 -> 2005-09 | B64: ='raw data'!U712 -> 711058.5 | C64: ='raw data'!V712 -> 304130.3 | D64: =E64-C64 -> 8329633.9 | E64: ='raw data'!AH712 -> 8633764.2 | F64: ='raw data'!AO712 -> 8075420.7 | G64: ='raw data'!AS712 -> 6892137.5 | H64: =E64-F64 -> 558343.5 | I64: =E64-G64 -> 1741626.7 | J64: =C64/E64*100 -> 3.522569 | K64: =D64/C64 -> 27.388372 | L64: =E64/C64 -> 28.388372 | M64: =F64/C64 -> 26.552503 | N64: =E64/F64 -> 1.0691411 | O64: =E64/H64 -> 15.463177 | P64: =E64/I64 -> 4.9572989
A65: ='raw data'!A713 -> 2005-10 | B65: ='raw data'!U713 -> 702515.5 | C65: ='raw data'!V713 -> 296316.6 | D65: =E65-C65 -> 8376140.3 | E65: ='raw data'!AH713 -> 8672456.9 | F65: ='raw data'!AO713 -> 8114409.2 | G65: ='raw data'!AS713 -> 6932267.9 | H65: =E65-F65 -> 558047.7 | I65: =E65-G65 -> 1740189 | J65: =C65/E65*100 -> 3.4167549 | K65: =D65/C65 -> 28.267536 | L65: =E65/C65 -> 29.267536 | M65: =F65/C65 -> 27.384255 | N65: =E65/F65 -> 1.0687724 | O65: =E65/H65 -> 15.540709 | P65: =E65/I65 -> 4.9836293
... A261: ='raw data'!A909 -> 2022-02 | B261: ='raw data'!U909 -> 1680648.9 | C261: ='raw data'!V909 -> 820644.5 | D261: =E261-C261 -> 21842259 | E261: ='raw data'!AH909 -> 22662904 | F261: ='raw data'!AO909 -> 20681666 | G261: ='raw data'!AS909 -> 36246796 | H261: =E261-F261 -> 1981237 | I261: =E261-G261 -> -13583893 | J261: =C261/E261*100 -> 3.6210916 | K261: =D261/C261 -> 26.615982 | L261: =E261/C261 -> 27.615982 | M261: =F261/C261 -> 25.201737 | N261: =E261/F261 -> 1.0957968 | O261: =E261/H261 -> 11.438765 | P261: =E261/I261 -> -1.6683659

Sheet results_new
A1: Time | B1: Consumer Credit | C1: Credit Card | D1: Other Asset | E1: Total Asset | F1: Deposits | G1: Total Liability | H1: Residual (NW) | I1: Net Worth | J1: Deposits / CC | K1: CC / TA | L1: OA / CC | M1: TA / CC | N1: TL / CC | O1: TA / TL | P1: TA / Deposits | Q1: TA / NW
A2: ='raw data'!A650 -> 2000-07 | B2: ='raw data'!U650 -> 531142 | C2: ='raw data'!V650 -> 211897.8 | D2: =E2-C2 -> 5693184 | E2: ='raw data'!AH650 -> 5905081.8 | F2: =SUM('raw data'!AI650:AK650) -> 4521704.5 | G2: ='raw data'!AO650 -> 5678886 | H2: =E2-G2 -> 226195.8 | I2: =E2-F2 -> 1383377.3 | J2: =F2/C2 -> 21.339082 | K2: =C2/E2 -> 0.035883974 | L2: =D2/C2 -> 26.867594 | M2: =E2/C2 -> 27.867594 | N2: =G2/C2 -> 26.800118 | O2: =E2/G2 -> 1.039831 | P2: =E2/F2 -> 1.3059416 | Q2: =E2/I2 -> 4.2685982
A3: ='raw data'!A651 -> 2000-08 | B3: ='raw data'!U651 -> 538855.4 | C3: ='raw data'!V651 -> 217854 | D3: =E3-C3 -> 5716299.2 | E3: ='raw data'!AH651 -> 5934153.2 | F3: =SUM('raw data'!AI651:AK651) -> 4564306.7 | G3: ='raw data'!AO651 -> 5714051.1 | H3: =E3-G3 -> 220102.1 | I3: =E3-F3 -> 1369846.5 | J3: =F3/C3 -> 20.951218 | K3: =C3/E3 -> 0.036711893 | L3: =D3/C3 -> 26.239129 | M3: =E3/C3 -> 27.239129 | N3: =G3/C3 -> 26.22881 | O3: =E3/G3 -> 1.0385194 | P3: =E3/F3 -> 1.3001215 | Q3: =E3/I3 -> 4.3319841
A4: ='raw data'!A652 -> 2000-09 | B4: ='raw data'!U652 -> 543717.1 | C4: ='raw data'!V652 -> 222410.9 | D4: =E4-C4 -> 5751305.6 | E4: ='raw data'!AH652 -> 5973716.5 | F4: =SUM('raw data'!AI652:AK652) -> 4578304.4 | G4: ='raw data'!AO652 -> 5736376.6 | H4: =E4-G4 -> 237339.9 | I4: =E4-F4 -> 1395412.1 | J4: =F4/C4 -> 20.584892 | K4: =C4/E4 -> 0.037231579 | L4: =D4/C4 -> 25.85892 | M4: =E4/C4 -> 26.85892 | N4: =G4/C4 -> 25.791796 | O4: =E4/G4 -> 1.0413745 | P4: =E4/F4 -> 1.304788 | Q4: =E4/I4 -> 4.2809694
A5: ='raw data'!A653 -> 2000-10 | B5: ='raw data'!U653 -> 544271.9 | C5: ='raw data'!V653 -> 220752.4 | D5: =E5-C5 -> 5770217.5 | E5: ='raw data'!AH653 -> 5990969.9 | F5: =SUM('raw data'!AI653:AK653) -> 4585167.3 | G5: ='raw data'!AO653 -> 5730192.1 | H5: =E5-G5 -> 260777.8 | I5: =E5-F5 -> 1405802.6 | J5: =F5/C5 -> 20.770634 | K5: =C5/E5 -> 0.036847523 | L5: =D5/C5 -> 26.138866 | M5: =E5/C5 -> 27.138866 | N5: =G5/C5 -> 25.957553 | O5: =E5/G5 -> 1.0455094 | P5: =E5/F5 -> 1.3065979 | Q5: =E5/I5 -> 4.2616011
A6: ='raw data'!A654 -> 2000-11 | B6: ='raw data'!U654 -> 548263.8 | C6: ='raw data'!V654 -> 222338.7 | D6: =E6-C6 -> 5768300.6 | E6: ='raw data'!AH654 -> 5990639.3 | F6: =SUM('raw data'!AI654:AK654) -> 4576630.5 | G6: ='raw data'!AO654 -> 5716039.2 | H6: =E6-G6 -> 274600.1 | I6: =E6-F6 -> 1414008.8 | J6: =F6/C6 -> 20.584048 | K6: =C6/E6 -> 0.037114353 | L6: =D6/C6 -> 25.943754 | M6: =E6/C6 -> 26.943754 | N6: =G6/C6 -> 25.708701 | O6: =E6/G6 -> 1.0480403 | P6: =E6/F6 -> 1.3089628 | Q6: =E6/I6 -> 4.2366351
A7: ='raw data'!A655 -> 2000-12 | B7: ='raw data'!U655 -> 555531.4 | C7: ='raw data'!V655 -> 228197.3 | D7: =E7-C7 -> 5839338.5 | E7: ='raw data'!AH655 -> 6067535.8 | F7: =SUM('raw data'!AI655:AK655) -> 4646582.5 | G7: ='raw data'!AO655 -> 5809431.8 | H7: =E7-G7 -> 258104 | I7: =E7-F7 -> 1420953.3 | J7: =F7/C7 -> 20.362127 | K7: =C7/E7 -> 0.037609551 | L7: =D7/C7 -> 25.58899 | M7: =E7/C7 -> 26.58899 | N7: =G7/C7 -> 25.457934 | O7: =E7/G7 -> 1.0444284 | P7: =E7/F7 -> 1.3058061 | Q7: =E7/I7 -> 4.2700459
A8: ='raw data'!A656 -> 2001-01 | B8: ='raw data'!U656 -> 558590.1 | C8: ='raw data'!V656 -> 230967.4 | D8: =E8-C8 -> 5920051.7 | E8: ='raw data'!AH656 -> 6151019.1 | F8: =SUM('raw data'!AI656:AK656) -> 4688421.9 | G8: ='raw data'!AO656 -> 5877247 | H8: =E8-G8 -> 273772.1 | I8: =E8-F8 -> 1462597.2 | J8: =F8/C8 -> 20.299063 | K8: =C8/E8 -> 0.037549453 | L8: =D8/C8 -> 25.631547 | M8: =E8/C8 -> 26.631547 | N8: =G8/C8 -> 25.446219 | O8: =E8/G8 -> 1.0465817 | P8: =E8/F8 -> 1.3119594 | Q8: =E8/I8 -> 4.2055455
A9: ='raw data'!A657 -> 2001-02 | B9: ='raw data'!U657 -> 557858 | C9: ='raw data'!V657 -> 229551.1 | D9: =E9-C9 -> 5908417.3 | E9: ='raw data'!AH657 -> 6137968.4 | F9: =SUM('raw data'!AI657:AK657) -> 4700436.3 | G9: ='raw data'!AO657 -> 5870782.7 | H9: =E9-G9 -> 267185.7 | I9: =E9-F9 -> 1437532.1 | J9: =F9/C9 -> 20.476645 | K9: =C9/E9 -> 0.037398547 | L9: =D9/C9 -> 25.739007 | M9: =E9/C9 -> 26.739007 | N9: =G9/C9 -> 25.575058 | O9: =E9/G9 -> 1.0455111 | P9: =E9/F9 -> 1.3058295 | Q9: =E9/I9 -> 4.2697957
A10: ='raw data'!A658 -> 2001-03 | B10: ='raw data'!U658 -> 557205.5 | C10: ='raw data'!V658 -> 228144.8 | D10: =E10-C10 -> 5960646.7 | E10: ='raw data'!AH658 -> 6188791.5 | F10: =SUM('raw data'!AI658:AK658) -> 4737073.4 | G10: ='raw data'!AO658 -> 5919212.6 | H10: =E10-G10 -> 269578.9 | I10: =E10-F10 -> 1451718.1 | J10: =F10/C10 -> 20.763451 | K10: =C10/E10 -> 0.036864192 | L10: =D10/C10 -> 26.126595 | M10: =E10/C10 -> 27.126595 | N10: =G10/C10 -> 25.944981 | O10: =E10/G10 -> 1.045543 | P10: =E10/F10 -> 1.3064589 | Q10: =E10/I10 -> 4.2630808
A11: ='raw data'!A659 -> 2001-04 | B11: ='raw data'!U659 -> 561350.2 | C11: ='raw data'!V659 -> 232200.8 | D11: =E11-C11 -> 5996841.9 | E11: ='raw data'!AH659 -> 6229042.7 | F11: =SUM('raw data'!AI659:AK659) -> 4783168.3 | G11: ='raw data'!AO659 -> 5948783.7 | H11: =E11-G11 -> 280259 | I11: =E11-F11 -> 1445874.4 | J11: =F11/C11 -> 20.599276 | K11: =C11/E11 -> 0.037277124 | L11: =D11/C11 -> 25.826104 | M11: =E11/C11 -> 26.826104 | N11: =G11/C11 -> 25.619135 | O11: =E11/G11 -> 1.047112 | P11: =E11/F11 -> 1.3022838 | Q11: =E11/I11 -> 4.3081492
A12: ='raw data'!A660 -> 2001-05 | B12: ='raw data'!U660 -> 566114.6 | C12: ='raw data'!V660 -> 235574.1 | D12: =E12-C12 -> 5983711.3 | E12: ='raw data'!AH660 -> 6219285.4 | F12: =SUM('raw data'!AI660:AK660) -> 4814665.4 | G12: ='raw data'!AO660 -> 5946266.5 | H12: =E12-G12 -> 273018.9 | I12: =E12-F12 -> 1404620 | J12: =F12/C12 -> 20.438008 | K12: =C12/E12 -> 0.037878001 | L12: =D12/C12 -> 25.400548 | M12: =E12/C12 -> 26.400548 | N12: =G12/C12 -> 25.241597 | O12: =E12/G12 -> 1.0459143 | P12: =E12/F12 -> 1.2917378 | Q12: =E12/I12 -> 4.4277352
A13: ='raw data'!A661 -> 2001-06 | B13: ='raw data'!U661 -> 564557.4 | C13: ='raw data'!V661 -> 233267.1 | D13: =E13-C13 -> 5974287.5 | E13: ='raw data'!AH661 -> 6207554.6 | F13: =SUM('raw data'!AI661:AK661) -> 4833647.1 | G13: ='raw data'!AO661 -> 5932611.4 | H13: =E13-G13 -> 274943.2 | I13: =E13-F13 -> 1373907.5 | J13: =F13/C13 -> 20.721512 | K13: =C13/E13 -> 0.037577938 | L13: =D13/C13 -> 25.611359 | M13: =E13/C13 -> 26.611359 | N13: =G13/C13 -> 25.432697 | O13: =E13/G13 -> 1.0463444 | P13: =E13/F13 -> 1.2842383 | Q13: =E13/I13 -> 4.5181751
... A43: ='raw data'!A691 -> 2003-12 | B43: ='raw data'!U691 -> 664772.1 | C43: ='raw data'!V691 -> 280989.7 | D43: =E43-C43 -> 7033550.5 | E43: ='raw data'!AH691 -> 7314540.2 | F43: =SUM('raw data'!AI691:AK691) -> 5631953.6 | G43: ='raw data'!AO691 -> 6930551.9 | H43: =E43-G43 -> 383988.3 | I43: =E43-F43 -> 1682586.6 | J43: =F43/C43 -> 20.043274 | K43: =C43/E43 -> 0.038415224 | L43: =D43/C43 -> 25.031346 | M43: =E43/C43 -> 26.031346 | N43: =G43/C43 -> 24.66479 | O43: =E43/G43 -> 1.0554052 | P43: =E43/F43 -> 1.2987572 | Q43: =E43/I43 -> 4.3471998
A44: ='raw data'!A692 -> 2004-01 | B44: ='raw data'!U692 -> 671934.4 | C44: ='raw data'!V692 -> 283276.6 | D44: =E44-C44 -> 7118876.4 | E44: ='raw data'!AH692 -> 7402153 | F44: =SUM('raw data'!AI692:AK692) -> 5684357.4 | G44: ='raw data'!AO692 -> 7023084 | H44: =E44-G44 -> 379069 | I44: =E44-F44 -> 1717795.6 | J44: =F44/C44 -> 20.066456 | K44: =C44/E44 -> 0.038269487 | L44: =D44/C44 -> 25.130478 | M44: =E44/C44 -> 26.130478 | N44: =G44/C44 -> 24.79232 | O44: =E44/G44 -> 1.0539747 | P44: =E44/F44 -> 1.302197 | Q44: =E44/I44 -> 4.3091 | S44: Avg TA/D | T44: Avg TA/NW
A45: ='raw data'!A693 -> 2004-02 | B45: ='raw data'!U693 -> 671297.8 | C45: ='raw data'!V693 -> 281560.2 | D45: =E45-C45 -> 7239054.6 | E45: ='raw data'!AH693 -> 7520614.8 | F45: =SUM('raw data'!AI693:AK693) -> 5749278.9 | G45: ='raw data'!AO693 -> 7130441.1 | H45: =E45-G45 -> 390173.7 | I45: =E45-F45 -> 1771335.9 | J45: =F45/C45 -> 20.419359 | K45: =C45/E45 -> 0.037438455 | L45: =D45/C45 -> 25.710504 | M45: =E45/C45 -> 26.710504 | N45: =G45/C45 -> 25.324748 | O45: =E45/G45 -> 1.0547194 | P45: =E45/F45 -> 1.3080971 | Q45: =E45/I45 -> 4.2457305 | R45: 2004 | S45: =AVERAGE(P44:P55) -> 1.2835543 | T45: =AVERAGE(Q44:Q55) -> 4.5341847
A46: ='raw data'!A694 -> 2004-03 | B46: ='raw data'!U694 -> 669655.6 | C46: ='raw data'!V694 -> 279474.5 | D46: =E46-C46 -> 7272080.8 | E46: ='raw data'!AH694 -> 7551555.3 | F46: =SUM('raw data'!AI694:AK694) -> 5828558.8 | G46: ='raw data'!AO694 -> 7160907.1 | H46: =E46-G46 -> 390648.2 | I46: =E46-F46 -> 1722996.5 | J46: =F46/C46 -> 20.855423 | K46: =C46/E46 -> 0.037008866 | L46: =D46/C46 -> 26.020552 | M46: =E46/C46 -> 27.020552 | N46: =G46/C46 -> 25.622757 | O46: =E46/G46 -> 1.0545529 | P46: =E46/F46 -> 1.2956128 | Q46: =E46/I46 -> 4.3828036 | R46: 2005 | S46: =AVERAGE(P56:P67) -> 1.258781 | T46: =AVERAGE(Q56:Q67) -> 4.8672367
A47: ='raw data'!A695 -> 2004-04 | B47: ='raw data'!U695 -> 672082.9 | C47: ='raw data'!V695 -> 281049.1 | D47: =E47-C47 -> 7357249.4 | E47: ='raw data'!AH695 -> 7638298.5 | F47: =SUM('raw data'!AI695:AK695) -> 5891009 | G47: ='raw data'!AO695 -> 7202602.1 | H47: =E47-G47 -> 435696.4 | I47: =E47-F47 -> 1747289.5 | J47: =F47/C47 -> 20.960782 | K47: =C47/E47 -> 0.036794726 | L47: =D47/C47 -> 26.177808 | M47: =E47/C47 -> 27.177808 | N47: =G47/C47 -> 25.627558 | O47: =E47/G47 -> 1.0604915 | P47: =E47/F47 -> 1.2966028 | Q47: =E47/I47 -> 4.3715128 | R47: 2006 | S47: =AVERAGE(P68:P79) -> 1.2443974 | T47: =AVERAGE(Q68:Q79) -> 5.0934118
A48: ='raw data'!A696 -> 2004-05 | B48: ='raw data'!U696 -> 677176.8 | C48: ='raw data'!V696 -> 284903.9 | D48: =E48-C48 -> 7379888.4 | E48: ='raw data'!AH696 -> 7664792.3 | F48: =SUM('raw data'!AI696:AK696) -> 6000669.7 | G48: ='raw data'!AO696 -> 7233687.2 | H48: =E48-G48 -> 431105.1 | I48: =E48-F48 -> 1664122.6 | J48: =F48/C48 -> 21.062083 | K48: =C48/E48 -> 0.037170466 | L48: =D48/C48 -> 25.90308 | M48: =E48/C48 -> 26.90308 | N48: =G48/C48 -> 25.38992 | O48: =E48/G48 -> 1.0595969 | P48: =E48/F48 -> 1.2773228 | Q48: =E48/I48 -> 4.605906
A49: ='raw data'!A697 -> 2004-06 | B49: ='raw data'!U697 -> 679977.5 | C49: ='raw data'!V697 -> 287433.6 | D49: =E49-C49 -> 7454905.4 | E49: ='raw data'!AH697 -> 7742339 | F49: =SUM('raw data'!AI697:AK697) -> 6060581.5 | G49: ='raw data'!AO697 -> 7331544.1 | H49: =E49-G49 -> 410794.9 | I49: =E49-F49 -> 1681757.5 | J49: =F49/C49 -> 21.085153 | K49: =C49/E49 -> 0.037124905 | L49: =D49/C49 -> 25.936096 | M49: =E49/C49 -> 26.936096 | N49: =G49/C49 -> 25.506914 | O49: =E49/G49 -> 1.0560312 | P49: =E49/F49 -> 1.2774911 | Q49: =E49/I49 -> 4.603719
A50: ='raw data'!A698 -> 2004-07 | B50: ='raw data'!U698 -> 680087 | C50: ='raw data'!V698 -> 287878.6 | D50: =E50-C50 -> 7557867.1 | E50: ='raw data'!AH698 -> 7845745.7 | F50: =SUM('raw data'!AI698:AK698) -> 6156965.3 | G50: ='raw data'!AO698 -> 7433368.8 | H50: =E50-G50 -> 412376.9 | I50: =E50-F50 -> 1688780.4 | J50: =F50/C50 -> 21.387367 | K50: =C50/E50 -> 0.036692318 | L50: =D50/C50 -> 26.253661 | M50: =E50/C50 -> 27.253661 | N50: =G50/C50 -> 25.821193 | O50: =E50/G50 -> 1.0554764 | P50: =E50/F50 -> 1.2742878 | Q50: =E50/I50 -> 4.6458058 | S50: Avg D/CC | T50: Avg CC/TA
A51: ='raw data'!A699 -> 2004-08 | B51: ='raw data'!U699 -> 683613.5 | C51: ='raw data'!V699 -> 290661.3 | D51: =E51-C51 -> 7586471.1 | E51: ='raw data'!AH699 -> 7877132.4 | F51: =SUM('raw data'!AI699:AK699) -> 6169053.8 | G51: ='raw data'!AO699 -> 7445370.8 | H51: =E51-G51 -> 431761.6 | I51: =E51-F51 -> 1708078.6 | J51: =F51/C51 -> 21.224201 | K51: =C51/E51 -> 0.03689938 | L51: =D51/C51 -> 26.100727 | M51: =E51/C51 -> 27.100727 | N51: =G51/C51 -> 25.615281 | O51: =E51/G51 -> 1.0579906 | P51: =E51/F51 -> 1.2768785 | Q51: =E51/I51 -> 4.611692 | S51: =AVERAGE(J8:J55) -> 21.292136 | T51: =AVERAGE(K8:K55) -> 0.036700477
A52: ='raw data'!A700 -> 2004-09 | B52: ='raw data'!U700 -> 686419.5 | C52: ='raw data'!V700 -> 294299.2 | D52: =E52-C52 -> 7666584.1 | E52: ='raw data'!AH700 -> 7960883.3 | F52: =SUM('raw data'!AI700:AK700) -> 6202452.8 | G52: ='raw data'!AO700 -> 7498189.3 | H52: =E52-G52 -> 462694 | I52: =E52-F52 -> 1758430.5 | J52: =F52/C52 -> 21.07533 | K52: =C52/E52 -> 0.036968159 | L52: =D52/C52 -> 26.050306 | M52: =E52/C52 -> 27.050306 | N52: =G52/C52 -> 25.478116 | O52: =E52/G52 -> 1.0617074 | P52: =E52/F52 -> 1.2835057 | Q52: =E52/I52 -> 4.5272664
A53: ='raw data'!A701 -> 2004-10 | B53: ='raw data'!U701 -> 684346.8 | C53: ='raw data'!V701 -> 291309 | D53: =E53-C53 -> 7682430.6 | E53: ='raw data'!AH701 -> 7973739.6 | F53: =SUM('raw data'!AI701:AK701) -> 6241305.6 | G53: ='raw data'!AO701 -> 7493249 | H53: =E53-G53 -> 480490.6 | I53: =E53-F53 -> 1732434 | J53: =F53/C53 -> 21.425035 | K53: =C53/E53 -> 0.036533548 | L53: =D53/C53 -> 26.372102 | M53: =E53/C53 -> 27.372102 | N53: =G53/C53 -> 25.722683 | O53: =E53/G53 -> 1.0641231 | P53: =E53/F53 -> 1.2775756 | Q53: =E53/I53 -> 4.6026224
A54: ='raw data'!A702 -> 2004-11 | B54: ='raw data'!U702 -> 680706.3 | C54: ='raw data'!V702 -> 287768.8 | D54: =E54-C54 -> 7721897.7 | E54: ='raw data'!AH702 -> 8009666.5 | F54: =SUM('raw data'!AI702:AK702) -> 6313141.4 | G54: ='raw data'!AO702 -> 7537779.5 | H54: =E54-G54 -> 471887 | I54: =E54-F54 -> 1696525.1 | J54: =F54/C54 -> 21.938241 | K54: =C54/E54 -> 0.035927688 | L54: =D54/C54 -> 26.833686 | M54: =E54/C54 -> 27.833686 | N54: =G54/C54 -> 26.193873 | O54: =E54/G54 -> 1.0626029 | P54: =E54/F54 -> 1.2687291 | Q54: =E54/I54 -> 4.721219
A55: ='raw data'!A703 -> 2004-12 | B55: ='raw data'!U703 -> 691415 | C55: ='raw data'!V703 -> 296868.7 | D55: =E55-C55 -> 7742069.1 | E55: ='raw data'!AH703 -> 8038937.8 | F55: =SUM('raw data'!AI703:AK703) -> 6358149.7 | G55: ='raw data'!AO703 -> 7548653.1 | H55: =E55-G55 -> 490284.7 | I55: =E55-F55 -> 1680788.1 | J55: =F55/C55 -> 21.41738 | K55: =C55/E55 -> 0.036928846 | L55: =D55/C55 -> 26.079102 | M55: =E55/C55 -> 27.079102 | N55: =G55/C55 -> 25.427582 | O55: =E55/G55 -> 1.06495 | P55: =E55/F55 -> 1.2643518 | Q55: =E55/I55 -> 4.7828384
A56: ='raw data'!A704 -> 2005-01 | B56: ='raw data'!U704 -> 693794.9 | C56: ='raw data'!V704 -> 303790.4 | D56: =E56-C56 -> 7792052.7 | E56: ='raw data'!AH704 -> 8095843.1 | F56: =SUM('raw data'!AI704:AK704) -> 6424894.4 | G56: ='raw data'!AO704 -> 7607596.5 | H56: =E56-G56 -> 488246.6 | I56: =E56-F56 -> 1670948.7 | J56: =F56/C56 -> 21.149103 | K56: =C56/E56 -> 0.037524245 | L56: =D56/C56 -> 25.649437 | M56: =E56/C56 -> 26.649437 | N56: =G56/C56 -> 25.042254 | O56: =E56/G56 -> 1.0641788 | P56: =E56/F56 -> 1.2600741 | Q56: =E56/I56 -> 4.8450578
A57: ='raw data'!A705 -> 2005-02 | B57: ='raw data'!U705 -> 690746.4 | C57: ='raw data'!V705 -> 299128.9 | D57: =E57-C57 -> 7874900.6 | E57: ='raw data'!AH705 -> 8174029.5 | F57: =SUM('raw data'!AI705:AK705) -> 6462188.8 | G57: ='raw data'!AO705 -> 7661914 | H57: =E57-G57 -> 512115.5 | I57: =E57-F57 -> 1711840.7 | J57: =F57/C57 -> 21.603358 | K57: =C57/E57 -> 0.036595036 | L57: =D57/C57 -> 26.326111 | M57: =E57/C57 -> 27.326111 | N57: =G57/C57 -> 25.614088 | O57: =E57/G57 -> 1.0668391 | P57: =E57/F57 -> 1.2649011 | Q57: =E57/I57 -> 4.7749943
A58: ='raw data'!A706 -> 2005-03 | B58: ='raw data'!U706 -> 693057.9 | C58: ='raw data'!V706 -> 299727.2 | D58: =E58-C58 -> 7968888.7 | E58: ='raw data'!AH706 -> 8268615.9 | F58: =SUM('raw data'!AI706:AK706) -> 6499953.9 | G58: ='raw data'!AO706 -> 7746512.2 | H58: =E58-G58 -> 522103.7 | I58: =E58-F58 -> 1768662 | J58: =F58/C58 -> 21.686233 | K58: =C58/E58 -> 0.036248775 | L58: =D58/C58 -> 26.587139 | M58: =E58/C58 -> 27.587139 | N58: =G58/C58 -> 25.845209 | O58: =E58/G58 -> 1.0673986 | P58: =E58/F58 -> 1.2721038 | Q58: =E58/I58 -> 4.6750684
A59: ='raw data'!A707 -> 2005-04 | B59: ='raw data'!U707 -> 693525.3 | C59: ='raw data'!V707 -> 301125.6 | D59: =E59-C59 -> 7999630.4 | E59: ='raw data'!AH707 -> 8300756 | F59: =SUM('raw data'!AI707:AK707) -> 6572787.5 | G59: ='raw data'!AO707 -> 7765176.6 | H59: =E59-G59 -> 535579.4 | I59: =E59-F59 -> 1727968.5 | J59: =F59/C59 -> 21.827395 | K59: =C59/E59 -> 0.036276889 | L59: =D59/C59 -> 26.56576 | M59: =E59/C59 -> 27.56576 | N59: =G59/C59 -> 25.787169 | O59: =E59/G59 -> 1.068972 | P59: =E59/F59 -> 1.2628974 | Q59: =E59/I59 -> 4.8037658
A60: ='raw data'!A708 -> 2005-05 | B60: ='raw data'!U708 -> 691829.1 | C60: ='raw data'!V708 -> 298997.3 | D60: =E60-C60 -> 8081607.6 | E60: ='raw data'!AH708 -> 8380604.9 | F60: =SUM('raw data'!AI708:AK708) -> 6603902.7 | G60: ='raw data'!AO708 -> 7834926.4 | H60: =E60-G60 -> 545678.5 | I60: =E60-F60 -> 1776702.2 | J60: =F60/C60 -> 22.086831 | K60: =C60/E60 -> 0.035677293 | L60: =D60/C60 -> 27.029032 | M60: =E60/C60 -> 28.029032 | N60: =G60/C60 -> 26.204004 | O60: =E60/G60 -> 1.0696469 | P60: =E60/F60 -> 1.2690382 | Q60: =E60/I60 -> 4.7169441
A61: ='raw data'!A709 -> 2005-06 | B61: ='raw data'!U709 -> 692900.4 | C61: ='raw data'!V709 -> 301594.9 | D61: =E61-C61 -> 8126343.4 | E61: ='raw data'!AH709 -> 8427938.3 | F61: =SUM('raw data'!AI709:AK709) -> 6690853.8 | G61: ='raw data'!AO709 -> 7877526.3 | H61: =E61-G61 -> 550412 | I61: =E61-F61 -> 1737084.5 | J61: =F61/C61 -> 22.184904 | K61: =C61/E61 -> 0.035785134 | L61: =D61/C61 -> 26.944565 | M61: =E61/C61 -> 27.944565 | N61: =G61/C61 -> 26.119561 | O61: =E61/G61 -> 1.0698712 | P61: =E61/F61 -> 1.2596208 | Q61: =E61/I61 -> 4.8517722
A62: ='raw data'!A710 -> 2005-07 | B62: ='raw data'!U710 -> 697638.4 | C62: ='raw data'!V710 -> 302440.1 | D62: =E62-C62 -> 8171457.1 | E62: ='raw data'!AH710 -> 8473897.2 | F62: =SUM('raw data'!AI710:AK710) -> 6730293.7 | G62: ='raw data'!AO710 -> 7939848.9 | H62: =E62-G62 -> 534048.3 | I62: =E62-F62 -> 1743603.5 | J62: =F62/C62 -> 22.253311 | K62: =C62/E62 -> 0.035690792 | L62: =D62/C62 -> 27.018431 | M62: =E62/C62 -> 28.018431 | N62: =G62/C62 -> 26.252633 | O62: =E62/G62 -> 1.0672618 | P62: =E62/F62 -> 1.259068 | Q62: =E62/I62 -> 4.8599909
A63: ='raw data'!A711 -> 2005-08 | B63: ='raw data'!U711 -> 705855.3 | C63: ='raw data'!V711 -> 302007.9 | D63: =E63-C63 -> 8269716.8 | E63: ='raw data'!AH711 -> 8571724.7 | F63: =SUM('raw data'!AI711:AK711) -> 6832019.6 | G63: ='raw data'!AO711 -> 8032491.9 | H63: =E63-G63 -> 539232.8 | I63: =E63-F63 -> 1739705.1 | J63: =F63/C63 -> 22.62199 | K63: =C63/E63 -> 0.035233038 | L63: =D63/C63 -> 27.382452 | M63: =E63/C63 -> 28.382452 | N63: =G63/C63 -> 26.59696 | O63: =E63/G63 -> 1.0671314 | P63: =E63/F63 -> 1.2546399 | Q63: =E63/I63 -> 4.9271136
... A261: ='raw data'!A909 -> 2022-02 | B261: ='raw data'!U909 -> 1680648.9 | C261: ='raw data'!V909 -> 820644.5 | D261: =E261-C261 -> 21842259 | E261: ='raw data'!AH909 -> 22662904 | F261: =SUM('raw data'!AI909:AK909) -> 36246796 | G261: ='raw data'!AO909 -> 20681666 | H261: =E261-G261 -> 1981237 | I261: =E261-F261 -> -13583893 | J261: =F261/C261 -> 44.168695 | K261: =C261/E261 -> 0.036210916 | L261: =D261/C261 -> 26.615982 | M261: =E261/C261 -> 27.615982 | N261: =G261/C261 -> 25.201737 | O261: =E261/G261 -> 1.0957968 | P261: =E261/F261 -> 0.6252388 | Q261: =E261/I261 -> -1.6683659
